Workbook
Name cfRep: INDEX(#REF!,1,Bois!Mun_col_num) : INDEX(#REF!,COUNTA(Mun_col),Bois!Mun_col_num)
Name cfRep: INDEX(#REF!,1,Mun_col_num) : INDEX(#REF!,COUNTA(Mun_col),Mun_col_num)
Name choix_affichage: #REF!
Name Mun_col_num: MATCH(Ville,Municipalite,0)
Name Mun_col_num: MATCH(Ville,Municipalite,0)
Name Municipalite: #REF!
Name Ville: #REF!

Sheet Bois
A1: No d'enr. | B1: SIA | C1: Date de l'acte ou de l'avant contrat | D1: Vendeur | E1: Acheteur | F1: Lots | G1: Prix de vente ($) | H1: Prix de vente redressé au temps ($) | I1: MRC | J1: Ville/Municipalité | K1: Adresse complète | L1: Latitude | M1: Longitude | N1: Superficie totale (ha) | O1: Zone agricole (CPTAQ) | P1: Topographie | Q1: Superficie boisée (ha) | R1: Superficie cultivée (ha) | S1: Feuillus/Résineux | T1: Proportion feuillus | U1: Proporition résineux | V1: Densité plantation | W1: Zones humides (ha) | X1: Zones humides types) | Y1: Bâtiments agricoles | Z1: Valeur contributive bâtiments agricoles ($) | AA1: Source valeur constributive bâtiments agricoles | AB1: Équipements | AC1: Superficie acéricole (ha) | AD1: Nombre d'entailles | AE1: Contingent acéricole (Livres) | AF1: Observations | AG1: Décisions CPTAQ | AH1: Taux unitaire global ($/ha) | AI1: $/entaille
A2: 22262068 | C2: 42487 | D2: Madeleine Therrien, | E2: Alain Paquet, Marlène Plamondon, | F2: 1826955 | G2: 52000 | I2: Jacques-Cartier | J2: Stoneham-et-Tewkesbury | K2: chemin plante, Stoneham-et-Tewkesbury | L2: 47.008199 | M2: -71.439817 | N2: 14.28 | O2: non | P2: déclivité | Q2: 14.28 | R2: 0 | S2: Resineux | T2: 0.4 | U2: 0.6 | AC2: 2 | AF2: enclavé, resineux | AH2: =Table2[[#This Row],[Prix de vente ($)]]/Table2[[#This Row],[Superficie totale (ha)]] -> 3641.4566
A3: 22486718 | C3: 42569 | D3: 9319-9644 QUÉBEC INC., | E3: Jean GAGNÉ, Jean-Simon GAGNÉ, | F3: 5748850 | G3: 74733.75 | I3: Jacques-Cartier | J3: Lac-Beauport | K3: Chemin de l'Orignal, Lac-Beauport | L3: 46.974046 | M3: -71.265846 | N3: 4 | O3: non | P3: legere declivite | Q3: 4 | R3: 0 | S3: Feuillus | T3: 0.6 | U3: 0.4 | AC3: 0 | AF3: accesible | AH3: =Table2[[#This Row],[Prix de vente ($)]]/Table2[[#This Row],[Superficie totale (ha)]] -> 18683.438
A4: 22 661 085 | C4: 42649 | F4: 5 085 264, 4 913 356 | G4: 133000 | I4: Les Appalaches | J4: Kinnear's Mills | K4: 5e rang, Kinnear's Mills | AH4: =Table2[[#This Row],[Prix de vente ($)]]/Table2[[#This Row],[Superficie totale (ha)]] -> #DIV/0!
A5: 22674380 | C5: 42657 | D5: 9319-9644 QUÉBEC INC., | E5: Louis-Robert COUTURE, | F5: 5748805 | G5: 80482 | I5: Jacques-Cartier | J5: Lac-Beauport | K5: chemin du chevreuil, Lac-Beauport | L5: 46.977771 | M5: -71.249590 | N5: 4.69 | O5: non | P5: legere declivite | Q5: 4.69 | R5: 0 | S5: Feuillus | T5: 0.6 | U5: 0.4 | AC5: 0 | AF5: accesible | AH5: =Table2[[#This Row],[Prix de vente ($)]]/Table2[[#This Row],[Superficie totale (ha)]] -> 17160.341
A6: 22845364 | C6: 42748 | D6: Gilles DUMONT, | E6: 9350-2185 QUÉBEC INC., | F6: 1496205 | G6: 40000 | I6: Jacques-Cartier | J6: Lac-Beauport | K6: Chemin de la Tournée, Lac-Beauport | L6: 46.994168 | M6: -71.330368 | N6: 19.58 | O6: non | P6: déclivité | Q6: 19.58 | R6: 0 | S6: Feuillus | T6: 0.7 | U6: 0.3 | AC6: 8 | AF6: enclavé | AH6: =Table2[[#This Row],[Prix de vente ($)]]/Table2[[#This Row],[Superficie totale (ha)]] -> 2042.9009
A7: 22999530 | C7: 42836 | D7: Sylvain BOUCHARD, | E7: Sarah BEAUDRY-MONTMINY, Jonathan CHEVANEL, | F7: 4015270 | G7: 25000 | I7: Jacques-Cartier | J7: Lac-Beauport | K7: Chemin de l'Eperon, Lac-Beauport | L7: 46.970935 | M7: -71.343376 | N7: 4.04 | O7: non | P7: Légère déclivité | Q7: 4.04 | R7: 0 | S7: Feuillus | T7: 0.85 | U7: 0.15 | AC7: 2.3 | AF7: enclavé | AH7: =Table2[[#This Row],[Prix de vente ($)]]/Table2[[#This Row],[Superficie totale (ha)]] -> 6188.1188
A8: 23017142 | C8: 42846 | D8: Darlène ANDELY, | E8: 9350-2185 QUÉBEC INC | F8: 4 950 989 | G8: 75000 | I8: Jacques-Cartier | J8: Stoneham-et-Tewkesbury | K8: Chemin de la Grand-ligne, Stoneham-et-Tewkesbury | L8: 46.976398 | M8: -71.397325 | N8: 14.41 | O8: non | P8: Légère déclivité | Q8: 14.28 | R8: 0 | S8: Feuillus | T8: 0.85 | U8: 0.15 | AC8: 14 | AF8: accesible | AH8: =Table2[[#This Row],[Prix de vente ($)]]/Table2[[#This Row],[Superficie totale (ha)]] -> 5204.7189
A9: 23035629 | C9: 42853 | D9: 9319-9644 QUÉBEC INC | E9: Jean-Jacques LACHANCE | F9: 5748847 | G9: 71859.38 | I9: Jacques-Cartier | J9: Lac-Beauport | K9: Chemin de l'Orignal, Lac-Beauport | L9: 46.972937 | M9: -71.265053 | N9: 4.15 | O9: non | P9: Légère déclivité | Q9: 4.15 | R9: 0 | S9: Feuillus | T9: 0.9 | U9: 0.1 | AC9: 4 | AF9: accesible | AH9: =Table2[[#This Row],[Prix de vente ($)]]/Table2[[#This Row],[Superficie totale (ha)]] -> 17315.513
A10: 23216736 | C10: 42921 | D10: Thomas Lepagne, | E10: Guy Roberge, | F10: 6111085 | G10: 20000 | I10: Jacques-Cartier | J10: Stoneham-et-Tewkesbury | K10: Chemin Whalen, Stoneham-et-Tewkesbury | L10: 47.031558 | M10: -71.300384 | N10: 17.42 | O10: non | P10: Légère déclivité | Q10: 17.42 | R10: 0 | S10: Feuillus | T10: 0.7 | U10: 0.3 | AC10: 1.4 | AF10: enclavé | AH10: =Table2[[#This Row],[Prix de vente ($)]]/Table2[[#This Row],[Superficie totale (ha)]] -> 1148.1056
B11: 24079958 | C11: 43255 | F11: 106-P, Paroisse St-François et suivants | G11: 219000 | I11: L'Ile-d'Orléans | J11: Saint-François-de-l'Île-d'Orléans | K11: Chemin Royal Saint-François-de-l'Île-d'Orléans | L11: 47.01169928504172 | M11: -70.8353380495719 | N11: 31.28 | O11: oui | P11: Légère pente | Q11: =0.9*N11 -> 28.152 | R11: =0.1*N11 -> 3.128 | S11: F | T11: 1 | U11: 0 | AC11: 6.7 | AF11: Peuplement peu dense. Nouveau lot 6 282 149 (?) | AH11: =Table2[[#This Row],[Prix de vente ($)]]/Table2[[#This Row],[Superficie totale (ha)]] -> 7001.2788 | AI11: =G11/AD11 -> #DIV/0!
A12: 28472646 | C12: 43604 | D12: MARCEL ST-PIERRE | E12: LES BLEUETS DU FJORD INC | F12: 4 307 834, 4 307 833, 4 307 831, 4 307 829 | G12: 2300000 | I12: L'Érable | J12: Princeville | K12: 3e Rang, Princeville | L12: 46.255515 | M12: -71.891197 | N12: 264.29 | O12: oui | P12: legère déclivité | Q12: 264.29 | R12: 0 | S12: Resineux | T12: 0.4 | U12: 0.6 | AC12: 57.1 | AF12: tres grande superficie, enclavé et presence de marècage et de tourbière | AH12: =Table2[[#This Row],[Prix de vente ($)]]/Table2[[#This Row],[Superficie totale (ha)]] -> 8702.5616
A13: 24977808 | C13: 43730 | D13: Frédéric BOUDREAULT | E13: Serge GAUTHIER | F13: 5 148 744 | G13: 20000 | I13: Manicouagan | J13: Ragueneau | K13: 2ieme rang,Ragueneau | L13: 49.094129 | M13: -68.510631 | N13: 42.48 | O13: non | P13: déclivité importante | Q13: 42,48 | R13: 0 | S13: mixte | T13: 0.5 | U13: 0.5 | AC13: 0 | AF13: zone humide (tourbière boisé) | AH13: =Table2[[#This Row],[Prix de vente ($)]]/Table2[[#This Row],[Superficie totale (ha)]] -> 470.80979
A14: 21646365 | C14: 43795 | F14: 37-1, 38-1,38-2,39-P,42-1-P | G14: 265000 | I14: L'Ile-d'Orléans | J14: Saint-François-de-l'Île-d'Orléans | K14: Chemin Royal Saint-François-de-l'Île-d'Orléans | L14: 47.00677149448989 | M14: ,-70.88060766039577 | N14: 29.91 | Y14: Cabane à sucre | AD14: 500 | AF14: Cabane à sucre équipée | AH14: =Table2[[#This Row],[Prix de vente ($)]]/Table2[[#This Row],[Superficie totale (ha)]] -> 8859.9131 | AI14: =G14/AD14 -> 530
A15: 28155797 | C15: 43820 | D15: JEAN-GUY McCUTCHEON | E15: GESTION KATE INC | F15: 5 135 333, 5 136 091 | G15: 45000 | I15: Les Appalaches | J15: Adstock | K15: 11 e rang, Adsyock | L15: 46.092829 | M15: -71.152622 | N15: =8.52+1.16 -> 9.68 | O15: oui | P15: déclivité | Q15: 9.68 | R15: 0 | S15: Feuillus | T15: 0.7 | U15: 0.3 | AC15: =0.9+5.1 -> 6 | AF15: servitude de passage | AH15: =Table2[[#This Row],[Prix de vente ($)]]/Table2[[#This Row],[Superficie totale (ha)]] -> 4648.7603
A16: 27663835 | C16: 43870 | D16: René LEMOYNE, Serge LEMOINE, Jean-Guy LEMOINE | E16: Martin RHÉAUME | F16: 3 698 485, 3 698 524 | G16: 180000 | I16: Les Maskoutains | J16: La Présentation | K16: Rue des Bas-Étangs, La présentation | L16: 45.690941 | M16: -73.026890 | N16: =5+4.19 -> 9.19 | O16: oui | P16: plane | Q16: 9.19 | R16: 0 | S16: Feuillus | T16: 0.65 | U16: 0.35 | AC16: =0.4+3.4 -> 3.8 | AF16: enclavé, presence d'un bâtiment | AH16: =Table2[[#This Row],[Prix de vente ($)]]/Table2[[#This Row],[Superficie totale (ha)]] -> 19586.507
A17: 25257302 | C17: 43900 | D17: Luc DESLAURIERS, Rémy GINGRAS | E17: MARC LABARRE MD INC | F17: 3 055 985, 3 055 990 | G17: 180000 | I17: Québec | J17: Saint-Augustin-de-Desmaures | K17: rang du Petit-Capsa, Saint-Augustin-de- Desmaures | L17: 46.771386 | M17: -71.595172 | N17: =21.55+14.69 -> 36.24 | O17: oui | P17: Plane | Q17: =Bois!$N2 -> 14.28 | S17: Mixte | T17: 0.5 | U17: 0.5 | AF17: Superficie coupe de 11,6 ha. 2 cours d'eau permanents. | AH17: =Table2[[#This Row],[Prix de vente ($)]]/Table2[[#This Row],[Superficie totale (ha)]] -> 4966.8874 | AI17: =Bois!#REF!/Bois!$AD2 -> #REF!
A18: 25698764 | C18: 44092 | D18: JALROU INC (Jacques et Pierre Roussin) | E18: Olivier BONNEAU, INITIAL5 INC (Pierre-Luc GIRARD) | F18: 3056045 | G18: 46500 | I18: Québec | J18: Saint-Augustin-de-Desmaures | K18: rang du Petit-Capsa, Saint-Augustin-de- Desmaures | L18: 46.775839 | M18: -71.528771 | N18: 9.94 | O18: oui | P18: Plane | Q18: =Bois!$N3 -> 4 | S18: Mixte (dominance résineux) | T18: 0.76 | U18: 0.24 | AF18: Servitude de passage. | AG18: 043813, 234861 (refus construction) et 023486 (refus) | AH18: =Table2[[#This Row],[Prix de vente ($)]]/Table2[[#This Row],[Superficie totale (ha)]] -> 4678.0684 | AI18: =Bois!$G3/Bois!$AD3 -> #DIV/0!
A19: 25771426 | C19: 44123 | D19: 9013-0998 QUÉBEC INC Denis LÉVEILLÉ | E19: VILLE DE CHAMBLY | F19: 2343104 | G19: 400000 | I19: La-Vallée-du-Richelieu | J19: Chambly | L19: 45.415208 | M19: -73.291752 | N19: 17.79 | O19: oui | P19: Plane | S19: Feuillus | T19: 1 | U19: 0 | V19: 80-90 % | AC19: 10.8 | AF19: Bordure Autoroute 10 | AG19: 444141 (corridor récréatif) | AH19: =Table2[[#This Row],[Prix de vente ($)]]/Table2[[#This Row],[Superficie totale (ha)]] -> 22484.542
B20: 26189122 | C20: 44145 | F20: 5347394 | G20: 100000 | I20: L'Islet | J20: Saint-Adalbert | K20: 281 Route 204 O. Saint-Adalbert | L20: 46.832026 | M20: -69.958992 | N20: 41.51 | O20: oui | P20: Déclivité | Q20: =N20 -> 41.51 | AC20: 18 | AD20: 800 | AF20: Potentiel 1000 entailles, comprend station de pompage, réservoir 1000 gallons, entrée électrique 200A, relâcheur CDL et tubulure 3 ans d'usage | AH20: =Table2[[#This Row],[Prix de vente ($)]]/Table2[[#This Row],[Superficie totale (ha)]] -> 2409.0581 | AI20: =G20/AD20 -> 125
A21: 25960460 | C21: 44146 | D21: Élizabeth SAVARD | E21: Denis ARSENAULT | F21: 3815365 | G21: 25000 | I21: La côte-de-Beaupré | J21: Saint-Joachim | K21: Route 138, Saint-Joachim | L21: 47.087231 | M21: -70.856026 | N21: 14.49 | O21: non | P21: legère déclivité | Q21: 14.49 | R21: 0 | S21: Feuillus | T21: 0.8 | U21: 0.2 | AC21: 0 | AF21: enclavé, pas de potentiel acéricole | AH21: =Table2[[#This Row],[Prix de vente ($)]]/Table2[[#This Row],[Superficie totale (ha)]] -> 1725.3278
A22: 25902207 | C22: 44168 | D22: 9266-1024 QUÉBEC INC Paul Miklis | E22: François Doucet, Nancy Coulombe | F22: 2 599 858, 2 599 863 | G22: 160000 | I22: La-Vallée-du-Richelieu | J22: Carignan | K22: Chemin Bellerive, Carignan | L22: 45.489065 | M22: -73.319346 | N22: 7.72 | O22: oui | P22: Plane | S22: Feuillus | T22: 0.9 | U22: 0.1 | V22: 80-89% | AC22: 2.1 | AH22: =Table2[[#This Row],[Prix de vente ($)]]/Table2[[#This Row],[Superficie totale (ha)]] -> 20725.389
A23: 26106753 | C23: 44168 | D23: Richard RACINE | E23: Alexandre JULIEN | F23: 3815209 | G23: 25000 | I23: La côte-de-Beaupré | J23: Saint-Joachim | K23: Rue de la Miche, Saint-Joachim | L23: 47.093106 | M23: -70.846615 | N23: 8.44 | O23: non | P23: legère déclivité | Q23: 7.24 | R23: 0 | S23: Feuillus | T23: 0.9 | U23: 0.1 | AC23: 2.3 | AF23: enclavé | AH23: =Table2[[#This Row],[Prix de vente ($)]]/Table2[[#This Row],[Superficie totale (ha)]] -> 2962.0853
A24: 25951684 | C24: 44183 | D24: Michel Bernard Henri KUN, Léopold Christian KUN | E24: 9418-1286 QUÉBEC INC Minying WU | F24: 2 601 589, 2 600 785 | G24: 340000 | I24: La-Vallée-du-Richelieu | J24: Carignan | K24: Chemin Bellerive, Carignan | L24: 45.417657 | M24: -73.371157 | N24: 25.96 | O24: oui | P24: Plane | R24: 3.9 | S24: Feuillus | T24: 1 | U24: 0 | V24: 60-69 % | AC24: 12 | AH24: =Table2[[#This Row],[Prix de vente ($)]]/Table2[[#This Row],[Superficie totale (ha)]] -> 13097.072
A25: 26114479 | C25: 44184 | D25: FERME BERNARD GAUTHIER INC | E25: CHARLES RHÉAUME | F25: 5719391, 5719402 | G25: 72500 | I25: Charlevoix | J25: Saint-Hilarion | K25: 1er rang Saint-Hilarion | L25: 47.583581 | M25: -70.304526 | N25: =(515709.594+713.4)/10000 -> 51.642299 | O25: oui | P25: déclivité | Q25: =Bois!$N4-Bois!#REF! -> #REF! | S25: Résineux | AF25: Terrain traversé par ligne hydro-Québec | AH25: =Table2[[#This Row],[Prix de vente ($)]]/Table2[[#This Row],[Superficie totale (ha)]] -> 1403.8879 | AI25: =Bois!$G4/Bois!$AD4 -> #DIV/0!
A26: 25960915 | C26: 44187 | D26: Michel CÔTÉ | E26: LORD'STACE INC | F26: 4 582 896, 4 582 898, 4 582 895, 4 582 897 | G26: 275000 | I26: La côte-de-Beaupré | J26: Chateau-Richer | K26: Chemin de la Mine , Chateau-Richer | L26: 46.978132 | M26: -71.082581 | N26: 79.36 | O26: oui | P26: legère déclivité | Q26: =79.36-2.7 -> 76.66 | R26: 0 | S26: Resineux | T26: 0.3 | U26: 0.7 | AC26: 4.3 | AF26: enclavé, servitude de passage | AH26: =Table2[[#This Row],[Prix de vente ($)]]/Table2[[#This Row],[Superficie totale (ha)]] -> 3465.2218
A27: 26145375 | C27: 44212 | D27: Raymond POMERLEAU | E27: Alexandre GUERTIN, Catherine LEBLOND | F27: 5286409 | G27: 200000 | I27: Val-Saint-François | J27: Stoke | K27: 11e rang Est Stoke | L27: 45.566664 | M27: -71.742207 | N27: 41.42 | O27: oui | P27: Plane | Q27: =Bois!$N5-6.5 -> -1.81 | S27: Mixte | T27: 0.55 | U27: 0.45 | V27: 0.8 | AF27: Environ 6 hectares terres et friches | AH27: =Table2[[#This Row],[Prix de vente ($)]]/Table2[[#This Row],[Superficie totale (ha)]] -> 4828.5852 | AI27: =Bois!$G5/Bois!$AD5 -> #DIV/0!
A28: 25995437 | C28: 44214 | D28: Serge Lessard | E28: Charles Bérubé, Catherine Arnautovitch | F28: 6212197 | G28: 190000 | I28: La côte-de-Beaupré | J28: Saint-Tite-des-Caps | K28: Avenue de la Montagne, Saint-Tite-des-Caps | L28: 47.087242 | M28: -70.803061 | N28: 17.69 | O28: non | P28: legère déclivité | Q28: 17.69 | R28: 0 | S28: Feuillus | T28: 1 | U28: 0 | AC28: 17.69 | AF28: enclavé, servitude de passage, tres grand potentiel acéricole | AH28: =Table2[[#This Row],[Prix de vente ($)]]/Table2[[#This Row],[Superficie totale (ha)]] -> 10740.531
A29: 26021098 | C29: 44223 | D29: INVESTISSEMENT SNDA INC | E29: Charles PERRON-GAUVREAU | F29: 4 582 936, 4 832 455 | G29: 375000 | I29: La côte-de-Beaupré | J29: Chateau-Richer | K29: Chemin de la Mine , Chateau-Richer | L29: 46.972116 | M29: -71.054997 | N29: 63.35 | O29: oui | P29: déclivité | Q29: 63.35 | R29: 0 | S29: Feuillus | T29: 0.7 | U29: 0.3 | AC29: 29 | AF29: enclavé, servitude de passage | AH29: =Table2[[#This Row],[Prix de vente ($)]]/Table2[[#This Row],[Superficie totale (ha)]] -> 5919.4949
A30: 26032402 | C30: 44228 | D30: Alain BOUTIN | E30: Réjean FONTAINE, Lucie MARQUIS | F30: 3 375 232 | G30: 17000 | I30: Bellechasse | J30: Saint-Anselme | K30: Chemin des Morins, Saint-Anselme | L30: 46.589837 | M30: -70.973579 | N30: 5.48 | O30: oui | P30: plane | Q30: 5.48 | R30: 0 | S30: Feuillus | T30: 0.65 | U30: 0.35 | AC30: 2.3 | AF30: enclavé | AH30: =Table2[[#This Row],[Prix de vente ($)]]/Table2[[#This Row],[Superficie totale (ha)]] -> 3102.1898
A31: 26073067 | C31: 44231 | D31: Lucien LECLERC | E31: Jean-Philippe MORIN | F31: 4479817 | G31: 12000 | I31: L'Islet | J31: Sainte-Louise | K31: Sainte-Louise | L31: 47.296726 | M31: -70.034757 | N31: 5.89 | O31: oui | P31: plane | Q31: =N31 -> 5.89 | AC31: 3.2 | AH31: =Table2[[#This Row],[Prix de vente ($)]]/Table2[[#This Row],[Superficie totale (ha)]] -> 2037.3514 | AI31: =G31/AD31 -> #DIV/0!
A32: 26130138 | C32: 44237 | D32: Yves TREMBLAY | E32: Maryse MORNEAU | F32: 4 917 664 | G32: 37000 | I32: Manicouagan | J32: Pointe-Lebel | K32: Rue Granier, PointeLebel | L32: 49.101 | M32: -68.206541 | N32: 3.25 | O32: non | P32: legere declivite | Q32: 3.25 | R32: 0 | S32: résineux | T32: 0.1 | U32: 0.9 | AC32: 0 | AF32: Zone humide (eau peu profonde) | AH32: =Table2[[#This Row],[Prix de vente ($)]]/Table2[[#This Row],[Superficie totale (ha)]] -> 11384.615
A33: 26303798 | C33: 44237 | D33: LA FERME PELLERAT (1997) INC (Gervais PELLETIER) | E33: Maxine PAQUET LESSARD, Christian MERCIER | F33: 4479790 | G33: 115000 | I33: L'Islet | J33: Sainte-Louise | K33: rang Bonnet Sainte-Louise | L33: 47.288848 | M33: -70.054129 | N33: 16.93 | O33: oui | P33: Forte déclivité | Q33: =N33 -> 16.93 | AC33: =2.4+7.3 -> 9.7 | AH33: =Table2[[#This Row],[Prix de vente ($)]]/Table2[[#This Row],[Superficie totale (ha)]] -> 6792.6757 | AI33: =G33/AD33 -> #DIV/0!
A34: 26147486 | C34: 44250 | D34: Dominic CLOUTIER, Alexandre CLOUTIER | E34: Daniel MUNOZ, Jean-François GAUTHIER, Jessica LANGLAIS, Tonio BARTOLO | F34: 3 387 451, 3 387 445, 3 632 106, 3 387 446 | G34: 158000 | I34: Lotbinière | J34: Saint-Apollinaire | K34: rang Saint-Lazare Saint-Apollinaire | L34: 46.615412 | M34: -71.403848 | N34: =18.86+2.3+0.33+0.74 -> 22.23 | O34: oui | P34: Plane | Q34: =Bois!$N6 -> 19.58 | S34: Feuillus | T34: 0.6 | U34: 0.4 | V34: 0.65 | AH34: =Table2[[#This Row],[Prix de vente ($)]]/Table2[[#This Row],[Superficie totale (ha)]] -> 7107.5124 | AI34: =Bois!$G6/Bois!$AD6 -> #DIV/0!
A35: 26183363 | C35: 44252 | D35: Albert BOURDEAU, Dixie ARBUTHNOT | E35: FLORIAN ROBERT & FILS INC | F35: 5944131 | G35: 700000 | I35: Papineau | J35: Ripon | K35: Chemin Viceroy, Ripon | L35: 45.844299 | M35: -75.106484 | N35: 82.84 | O35: non | P35: déclivité | Q35: 77.84 | R35: 0 | S35: Feuillus | T35: 0.6 | U35: 0.4 | AC35: 22.5 | AF35: presence de batiments, tres accesible | AH35: =Table2[[#This Row],[Prix de vente ($)]]/Table2[[#This Row],[Superficie totale (ha)]] -> 8450.0241
A36: 26115144 | C36: 44260 | D36: DÉBOISEMENT G.C.G. INC (Carl BOULET) | E36: Mathieu BERNIÈRE, Isabelle CHABOT | F36: 6 417 583 | G36: 34500 | I36: Dorchester | J36: Saint-Luc-de- Bellechasse | K36: 12e Rang Saint-Luc-de- Bellechasse | L36: 46.523723 | M36: -70.470488, | N36: 1.64 | O36: non | P36: Plane | Q36: 1.64 | S36: Feuillus | T36: 0.9 | U36: 0.1 | AF36: Densité couvert 90-100% | AH36: =Table2[[#This Row],[Prix de vente ($)]]/Table2[[#This Row],[Superficie totale (ha)]] -> 21036.585 | AI36: =Bois!$G7/Bois!$AD7 -> #DIV/0!
A37: 26171908 | C37: 44284 | D37: 9155-5904 QUÉBEC INC | E37: GESTION FRANCOIS ROUSSIN INC | F37: 3 813 929, 3 815 781 | G37: 335000 | I37: La côte-de-Beaupré | J37: Sainte-Anne-de-Beaupré | K37: Avenue-Royale, Sainte-Anne-de-Beaupré | L37: 47.018347 | M37: -70.961798 | N37: 46.21 | O37: oui | P37: déclivité | Q37: 40.93 | R37: 2.4 | S37: Feuillus | T37: 0.9 | U37: 0.1 | AC37: 19.5 | AH37: =Table2[[#This Row],[Prix de vente ($)]]/Table2[[#This Row],[Superficie totale (ha)]] -> 7249.5131
A38: 26199842 | C38: 44295 | D38: Roland RACINE | E38: J-M Leclerc Excavation inc | F38: 6 212 177, 6 212 148 | G38: 150000 | I38: La côte-de-Beaupré | J38: Saint-Tite-des-Caps | K38: Route 138, Saint-Tite-des-Caps | L38: 47.116667 | M38: -70.809745 | N38: =16.71+13.99 -> 30.7 | O38: non | P38: legère déclivité | Q38: =30.7-4.1 -> 26.6 | R38: 0 | S38: Feuillus | T38: 0.7 | U38: 0.3 | AC38: 5.7 | AF38: accesible | AH38: =Table2[[#This Row],[Prix de vente ($)]]/Table2[[#This Row],[Superficie totale (ha)]] -> 4885.9935
A39: 26206431 | C39: 44298 | D39: François ROBERGE | E39: Ghislain SÉVIGNY, Danielle LAVOIE | F39: 4735650 | G39: 40000 | I39: Jacques-Cartier | J39: Stoneham-et-Tewkesbury | K39: chemin du Bruant Stoneham-et-Tewkesbury | L39: 46.941059 | M39: -71.364145 | N39: 8.25 | O39: non | P39: pente | Q39: 8.25 | S39: F | T39: 0.8 | U39: 0.2 | V39: 70-79% | AC39: 3.5 | AF39: Enclavé. | AH39: =Table2[[#This Row],[Prix de vente ($)]]/Table2[[#This Row],[Superficie totale (ha)]] -> 4848.4848 | AI39: #DIV/0!
A40: 26221712 | C40: 44302 | D40: LES ENTREPRISES FORESTIÈRES LEBLANC INC | E40: Gabriel LEVESQUE-NADEAU, Lory PLANTE-MICHELIN | F40: 6411246 | G40: 40000 | I40: Dorchester | J40: Saint-Luc-de- Bellechasse | K40: route Laflamme, Saint-Luc-de-Bellechasse | L40: 46.544574 | M40: -70.556879 | N40: 3.49 | O40: non | P40: Plane | Q40: 3.49 | S40: Mixte (dominance feuillus) | T40: 0.7 | U40: 0.3 | AF40: Densité couvert 80-89% | AH40: =Table2[[#This Row],[Prix de vente ($)]]/Table2[[#This Row],[Superficie totale (ha)]] -> 11461.318 | AI40: =Bois!$G8/Bois!$AD8 -> #DIV/0!
A41: 26256714 | C41: 44315 | D41: Raymond GAGNON | E41: Patrick-Emmanuel BOULANGER-NADEAU, Annie FOURNIER | F41: 3 387 480, 3 387 481 | G41: 220000 | I41: Lotbinière | J41: Saint-Apollinaire | K41: Route des Ruisseaux Saint-Apollinaire | L41: 46.616752 | M41: -71.429167 | N41: =10.42+12.11 -> 22.53 | O41: oui | P41: Plane | Q41: =Bois!$N9 -> 4.15 | S41: Mixte | T41: 0.5 | U41: 0.5 | V41: 0.65 | AH41: =Table2[[#This Row],[Prix de vente ($)]]/Table2[[#This Row],[Superficie totale (ha)]] -> 9764.7581 | AI41: =Bois!$G9/Bois!$AD9 -> #DIV/0!
A42: 26287971 | C42: 44326 | D42: Ariane JOLICOEUR, Lucie-Gabrielle JOLICOEUR | E42: Érika MILLER-JOLICOEUR, Vincent ARPIN-BÉLANGER | F42: 6 187 086, 6 186 477 | G42: 90000 | I42: L'Ile-d'Orléans | J42: Saint-Pierre | K42: Chemin Royal Saint-Pierre | L42: 46.878592 | M42: -71.102815 | N42: =7.58+0.08 -> 7.66 | O42: oui | P42: Pente | Q42: 4.8 | R42: 2.18 | S42: F | T42: 0.9 | U42: 0.1 | AC42: 0.5 | AH42: =Table2[[#This Row],[Prix de vente ($)]]/Table2[[#This Row],[Superficie totale (ha)]] -> 11749.347 | AI42: =G42/AD42 -> #DIV/0!
A43: 26286281 | C43: 44326 | D43: Philippe Olivier BOUCHER | E43: INVESTISSEMENTS BOUCHER INC Philippe Olivier BOUCHER | F43: 1 912 387, 2 402 410 | G43: 475000 | J43: Boucherville | K43: 1820 rue Eiffel, Boucherville | L43: 45.571831 | M43: -73.365700 | N43: =6.34+4.17 -> 10.51 | O43: oui | P43: Plane | S43: Feuillus | T43: 1 | U43: 0 | V43: 70-79% | AF43: Bordure Autoroute 20 | AH43: =Table2[[#This Row],[Prix de vente ($)]]/Table2[[#This Row],[Superficie totale (ha)]] -> 45195.052
A44: 26286281 | C44: 44326 | D44: Philippe Olivier BOUCHER, INVESTISSEMENTS BOUCHER INC | E44: 146993 CANADA INC, Stéphane SAVARIA | F44: 1 912 387, 2 402 410 | G44: 475000 | J44: Boucherville | K44: 1820 rue Eiffel, Boucherville | L44: 45.571932 | M44: -73.365432 | N44: =6.34+4.17 -> 10.51 | O44: oui | P44: Plane | S44: Feuillus | T44: 1 | U44: 0 | V44: 70-79 % | AF44: Friche sur 8000 mc | AG44: 188507 (refus nouvel usage golf) | AH44: =Table2[[#This Row],[Prix de vente ($)]]/Table2[[#This Row],[Superficie totale (ha)]] -> 45195.052
A45: 26288902 | C45: 44327 | D45: Bruno DUMONT, Francis DESJARDINS | E45: Jean-Frédéric MONGRAIN | F45: 3198255 | G45: 28000 | I45: Bellechasse | J45: La Durantaye | K45: La Durantaye | L45: 46.783304 | M45: -70.873876 | N45: 4.75 | O45: oui | P45: plane | Q45: =N45 -> 4.75 | S45: Résineux | T45: 0.1 | U45: 0.9 | AC45: 0 | AH45: =Table2[[#This Row],[Prix de vente ($)]]/Table2[[#This Row],[Superficie totale (ha)]] -> 5894.7368 | AI45: #DIV/0!
A46: 26425583 | C46: 44333 | D46: Pierre LECLERC, Patricia TREMBLAY | E46: SERVICES CONSEILS INFOLITE INC | F46: 5 892 418,5 893 109 | G46: 297000 | I46: Arthabaska | J46: Saint-Norbert-d'Arthabaska | K46: Rang 1e Ouest, Saint-Norbert-d'Arthabaska | L46: 46.103700 | M46: -71.776189 | N46: 19.02 | O46: oui | P46: legère déclivité | Q46: 19.02 | R46: 0 | S46: Feuillus | T46: 0.75 | U46: 0.25 | AC46: 6.2 | AF46: Pres d'un cours d'eau, presence de bâtiments | AH46: =Table2[[#This Row],[Prix de vente ($)]]/Table2[[#This Row],[Superficie totale (ha)]] -> 15615.142
A47: 26340830 | C47: 44343 | D47: CLAUDE DUPONT | E47: FRANCOIS ROUSSIN | F47: 3 813 851, 3 815 921 | G47: 835000 | I47: La côte-de-Beaupré | J47: Sainte-Anne-de-Beaupré | K47: Avenue-Royale, Sainte-Anne-de-Beaupré | L47: 47.021543 | M47: -70.960850 | N47: 51.72 | O47: oui | P47: déclivité | Q47: 39.3 | R47: 7.1 | S47: Feuillus | T47: 0.6 | U47: 0.4 | Y47: 2 | AC47: 10.2 | AF47: presence de batiment agricole et d'une maison | AH47: =Table2[[#This Row],[Prix de vente ($)]]/Table2[[#This Row],[Superficie totale (ha)]] -> 16144.625
A48: 26378839 | C48: 44354 | D48: François AUDET | E48: Jean-Philippe THOMERSON, Alexandre DUPLAIN-GOSSELIN, Mathieu FERLAND | F48: 2 110 331, 2 110 330, 1 828 483 | G48: 330000 | I48: Jacques-Cartier | J48: Stoneham-et-Tewkesbury | K48: Stoneham-et-Tewkesbury | L48: 47.032253 | M48: -71.365840 | N48: =42.8+41.32+40.12 -> 124.24 | O48: non | P48: très forte pente | Q48: =N48 -> 124.24 | S48: F | T48: 0.8 | U48: 0.2 | V48: 80-89% | AC48: 16.4 | AF48: Enclavé, servitude de passage | AH48: =Table2[[#This Row],[Prix de vente ($)]]/Table2[[#This Row],[Superficie totale (ha)]] -> 2656.1494 | AI48: #DIV/0!
A49: 26504832 | C49: 44391 | D49: GUY CROTEAU | E49: PAYSAGISTE 2000 INC (Clément CÔTÉ) | F49: 3 383 234, 3 584 385 | G49: 400000 | I49: Lotbinière | J49: Saint-Apollinaire | K49: Rang du Bois-Joly Saint-Apollinaire | L49: 46.580728 | M49: -71.517787 | N49: 20.37 | O49: oui | P49: Plane | Q49: =15.18+5.19 -> 20.37 | S49: Mixte | T49: 0.55 | U49: 0.45 | V49: 0.8 | AH49: =Table2[[#This Row],[Prix de vente ($)]]/Table2[[#This Row],[Superficie totale (ha)]] -> 19636.721 | AI49: =Bois!$G10/Bois!$AD10 -> #DIV/0!
A50: 26568918 | C50: 44414 | D50: Nancy PAQUET, Marc BEAUMONT | E50: Stéphanie BELISLE, Christian BLANCHETTE | F50: 3 056 058, 3 056 063, 3 056 066 | G50: 80000 | I50: Québec | J50: Saint-Augustin-de-Desmaures | K50: route de Fossambault, Saint-Augustin-de-Desmaures | L50: 46.785413 | M50: -71.515296 | N50: =1.46+1.07+0.98 -> 3.51 | O50: oui | P50: légère déclivité | Q50: 3.51 | S50: Mixte (dominance feuillus) | T50: 0.65 | U50: 0.35 | AF50: servitudes de passage, enclavés | AH50: =Table2[[#This Row],[Prix de vente ($)]]/Table2[[#This Row],[Superficie totale (ha)]] -> 22792.023 | AI50: =Bois!$G11/Bois!$AD11 -> #DIV/0!
A51: 26629727 | C51: 44440 | D51: Bernard GUAY, Mariette LEBEL | E51: Josianne GUAY | F51: 5287010 | G51: 90000 | I51: Val-Saint-François | J51: Stoke | K51: 4e rang Ouest Stoke | L51: 45.487975 | M51: -71.849450 | N51: 39.43 | O51: oui | P51: Déclivité | Q51: =Bois!$N12 -> 264.29 | S51: Feuillus | T51: 0.75 | U51: 0.25 | V51: 0.75 | AF51: Traversé par ligne HydroQuébec | AH51: =Table2[[#This Row],[Prix de vente ($)]]/Table2[[#This Row],[Superficie totale (ha)]] -> 2282.526 | AI51: =Bois!$G12/Bois!$AD12 -> #DIV/0!
A52: 27127821 | C52: 44460 | D52: Gilles GUÉRARD | E52: SOGETEL MOBILITÉ INC (Richard BIRON, Audrey BÉDARD) | F52: 6454294 | G52: 20000 | I52: Dorchester | J52: Saint-Luc-de- Bellechasse | K52: Rang 9 Saint-Luc-de-Bellechasse | L52: 46.520056 | M52: -70.500239 | N52: 0.49 | O52: non | P52: Plane | Q52: 0.49 | S52: Mixte (dominance résineux) | T52: 0.7 | U52: 0.3 | AF52: Densité couvert 70-79% | AH52: =Table2[[#This Row],[Prix de vente ($)]]/Table2[[#This Row],[Superficie totale (ha)]] -> 40816.327 | AI52: =Bois!$G13/Bois!$AD13 -> #DIV/0!
A53: 26702026 | C53: 44468 | D53: FERME GALOUMAR INC (Doris MORNEAU) | E53: GESTION MAT-LAU INC (Jean-Pierre HARTON) | F53: 4479714 | G53: 50000 | I53: L'Islet | J53: Sainte-Louise | K53: rang Bonnet Sainte-Louise | L53: 47.280665 | M53: -70.074458 | N53: 7.46 | O53: oui | P53: Forte déclivité | Q53: =N53 -> 7.46 | AC53: 4.8 | AH53: =Table2[[#This Row],[Prix de vente ($)]]/Table2[[#This Row],[Superficie totale (ha)]] -> 6702.4129 | AI53: =G53/AD53 -> #DIV/0!
A54: 26726692 | C54: 44477 | D54: TRANSPORT LIONEL VACHON & FILS INC | E54: Steeve LAFONTAINE et Nadia TANGUAY | F54: 6451734 | G54: 10000 | I54: Dorchester | J54: Saint-Luc-de- Bellechasse | K54: Route du Dix Saint-Luc-de- Bellechasse | L54: 46.515313 | M54: -70.480309 | N54: 0.71 | O54: non | P54: Plane | Q54: 0.71 | S54: Mixte (dominance résineux) | T54: 0.47 | U54: 0.53 | AF54: Densité couvert 60-69% | AH54: =Table2[[#This Row],[Prix de vente ($)]]/Table2[[#This Row],[Superficie totale (ha)]] -> 14084.507 | AI54: =Bois!$G15/Bois!$AD15 -> #DIV/0!
A55: 26985131 | C55: 44477 | D55: Frédéric DION | E55: Linda PRATTE | F55: 6460101, 5 036 859 | G55: 25500 | I55: Dorchester | J55: Saint-Luc-de- Bellechasse | K55: chemin St-Abdon St-Luc-de-Bellechasse | L55: 46.487023 | M55: -70.449910 | N55: =0.12+1.69 -> 1.81 | O55: non | P55: Plane | Q55: =0.12+1.69 -> 1.81 | S55: Résineux | T55: 0.9 | U55: 0.1 | AF55: Densité couvert 80-89% | AH55: =Table2[[#This Row],[Prix de vente ($)]]/Table2[[#This Row],[Superficie totale (ha)]] -> 14088.398 | AI55: =Bois!$G14/Bois!$AD14 -> 530
A56: 27281279 | C56: 44481 | D56: 9245-4958 QUÉBEC INC | E56: Richard JEAN, Edith MOINEAU | F56: 6464395 | G56: 110000 | I56: Montmagny | J56: Sainte-Euphémie-sur-Rivière-du-Sud | K56: Rg Ste-Anne E. Sainte-Euphémie-sur-Rivière-du-Sud | L56: 46.768245 | M56: -70.411357 | N56: =591217.21/10.7639/10000 -> 5.4925929 | O56: oui | P56: Déclivité | Q56: =N56 -> 5.4925929 | S56: Résineux | T56: 0.45 | U56: 0.55 | V56: 0.75 | AC56: 1.6 | AD56: 1000 | AF56: Cabane et remise, tubulure, pas d'équipements | AH56: =Table2[[#This Row],[Prix de vente ($)]]/Table2[[#This Row],[Superficie totale (ha)]] -> 20026.971 | AI56: =G56/AD56 -> 110
A57: 27656363 | C57: 44481 | D57: Succession Andrei Bella SCHWARZ | E57: Jean-Philippe BEAUDET, David BEAUDET | F57: 5772387 | G57: 80000 | I57: Drummond | J57: Lefebre | K57: Rue Jeanne-d'Arc, Lefevbre | L57: 45.707763 | M57: -72.429891 | N57: 6.51 | O57: oui | P57: plane | Q57: 6.51 | R57: 0 | S57: Resineux | T57: 0.35 | U57: 0.65 | AC57: 0 | AF57: Pres d'un cours d'eau, resineux | AH57: =Table2[[#This Row],[Prix de vente ($)]]/Table2[[#This Row],[Superficie totale (ha)]] -> 12288.786
A58: 27538693 | C58: 44481 | D58: Succession Paul-René BERNIER | E58: ÉRABLIÈRE CHOUINARD MORNEAU S.E.N.C., | F58: 4634225 | G58: 75000 | I58: L'Islet | J58: Saint-Aubert | K58: Saint-Aubert | L58: 47.141669 | M58: -70.198672 | N58: 20.2 | O58: oui | P58: Forte déclivité | Q58: =Bois!$N16 -> 9.19 | AC58: 12.1 | AH58: =Table2[[#This Row],[Prix de vente ($)]]/Table2[[#This Row],[Superficie totale (ha)]] -> 3712.8713 | AI58: =Bois!$G16/Bois!$AD16 -> #DIV/0!
A59: 27200589 | C59: 44515 | D59: Benoit THERRIEN | E59: Tommy ALLARD-GAUVREAU | F59: 5892356 | G59: 162000 | I59: Arthabaska | J59: Saint-Norbert-d'Arthabaska | K59: Route de Sainte-Sophie, Saint-Norbert-d'Arthabaska | L59: 46.112592 | M59: -71.802278 | N59: 5.83 | O59: oui | P59: plane | Q59: 5.83 | R59: 0 | S59: Feuillus | T59: 0.9 | U59: 0.1 | AC59: 5.83 | AF59: presence de cabane à sucre, fort potentiel acericole | AH59: =Table2[[#This Row],[Prix de vente ($)]]/Table2[[#This Row],[Superficie totale (ha)]] -> 27787.307
A60: 26994774 | C60: 44518 | D60: LES ENTREPRISES RENALD MERCIER LTÉE | E60: ÉRABLIÈRES LUCAN INC | F60: 5691506 | G60: 525000 | I60: Les Appalaches | J60: Saint-Julien | K60: 4 e rang, Saint-Julien | L60: 45.983012 | M60: -71.541817 | N60: 32.78 | O60: oui | P60: déclivité | Q60: 32.78 | R60: 0 | S60: Feuillus | T60: 0.85 | U60: 0.15 | AC60: 30.3 | AF60: tres accesible, presence probable de cabane á sucre | AH60: =Table2[[#This Row],[Prix de vente ($)]]/Table2[[#This Row],[Superficie totale (ha)]] -> 16015.863
A61: 26850829 | C61: 44526 | D61: Frédéric DION | E61: Benoît LAFLAMME | F61: 6460102 | G61: 17000 | I61: Dorchester | J61: Saint-Luc-de- Bellechasse | K61: chemin St-Abdon St-Luc-de-Bellechasse | L61: 46.485808 | M61: -70.451185 | N61: 0.84 | O61: non | P61: Plane | Q61: =0.84-0.17 -> 0.67 | S61: Mixte (dominance résineux) | T61: 0.7 | U61: 0.3 | AF61: Densité couvert 50-59% | AH61: =Table2[[#This Row],[Prix de vente ($)]]/Table2[[#This Row],[Superficie totale (ha)]] -> 20238.095 | AI61: =Bois!$G17/Bois!$AD17 -> #DIV/0!
A62: 26861627 | C62: 44531 | D62: 2968-1608 QUÉBEC INC | E62: Éric LAROUCHE | F62: 6167164 | G62: 145000 | I62: Montmagny | J62: Lac-Frontière | K62: 110-116 Route 204 | L62: 46.654208 | M62: -70.039292 | N62: 31.65 | O62: non dispo | P62: déclivité | Q62: 31.65 | S62: Résineux | T62: 0.3 | U62: 0.7 | V62: 0.75 | AC62: 8.7 | AF62: Potentiel acéricole sur parcelle de la terre pas de mention du nombre d'entailles | AH62: =Table2[[#This Row],[Prix de vente ($)]]/Table2[[#This Row],[Superficie totale (ha)]] -> 4581.3586
A63: 26887463 | C63: 44540 | F63: 3926646 | G63: 14500 | J63: Deschambault-Grondines | K63: 2e rang Ouest Deschambault-Grondines | N63: 6.85 | P63: Plane | Q63: 0 | AH63: =Table2[[#This Row],[Prix de vente ($)]]/Table2[[#This Row],[Superficie totale (ha)]] -> 2116.7883
A64: 26994037 | C64: 44567 | D64: Lucien HUOT | E64: QUARTIER BEAU-RIVAGE INC | F64: 3 283 323, 4 090 288 | G64: 220000 | I64: Lévis | J64: Lévis | K64: Chemin Petit-Saint Jean, Lévis | L64: 46.673291 | M64: -71.303635 | N64: 25.05 | O64: oui | P64: plane | Q64: 25.05 | R64: 0 | S64: Resineux | T64: 0.4 | U64: 0.6 | AC64: 5 | AF64: enclavé,potentiel acéricole | AH64: =Table2[[#This Row],[Prix de vente ($)]]/Table2[[#This Row],[Superficie totale (ha)]] -> 8782.4351
A65: 27049975 | C65: 44571 | D65: Dan Élie LEBEAU | E65: Rémi FONTAINE | F65: 5877871 | G65: 55000 | I65: Chaudière-Appalaches | J65: Saint-Édouard-de-Lotbinière | K65: Rang St-Charles Saint-Édouard-de-Lotbinière | L65: 46.592772 | M65: -71.791071 | N65: 11.44 | O65: oui | P65: plane | Q65: =N65 -> 11.44 | S65: MR | T65: 0.4 | U65: 0.6 | AF65: 50% da la superficie en dénudé humide (peuplement très épars) | AH65: =Table2[[#This Row],[Prix de vente ($)]]/Table2[[#This Row],[Superficie totale (ha)]] -> 4807.6923 | AI65: =G65/AD65 -> #DIV/0!
A66: 26944077 | C66: 44574 | D66: MICHEL MORIN, MICHELLE LACASSE | E66: GESTION HÉLÈNE ET JEAN-PAUL MOREAU INC | F66: 4270040 | G66: 160000 | I66: Lotbinière | J66: Saint-Apollinaire | K66: Rang Gaspé Saint-Apollinaire | L66: 46.626610 | M66: -71.438196 | N66: 29.63 | O66: oui | P66: Plane | Q66: =Bois!$N18 -> 9.94 | S66: Résineux | T66: 0.1 | U66: 0.9 | V66: 0.85 | AH66: =Table2[[#This Row],[Prix de vente ($)]]/Table2[[#This Row],[Superficie totale (ha)]] -> 5399.9325 | AI66: =Bois!$G18/Bois!$AD18 -> #DIV/0!
A67: 26959251 | C67: 44581 | D67: 9424-1882 QUÉBEC INC. | E67: BRUNET & MICHAUDVILLE INC | F67: 5 090 257, 5 090 267 | G67: 88450 | I67: antoine-labelle | J67: Ferme-neuve | L67: 46.651598 | M67: -75.501995 | N67: 85.02 | O67: non | P67: déclivité importante | Q67: 85.02 | S67: feuillus | T67: 0.9 | U67: 0.1 | V67: 0.85 | AF67: la vente comprend plusieurs terre boisée et agricoles, qui ont été séparées par prix, celle-ci est a ferme-neuve. Potentiel acéricole dans le boisé. | AH67: =Table2[[#This Row],[Prix de vente ($)]]/Table2[[#This Row],[Superficie totale (ha)]] -> 1040.3434
A68: 27069738 | B68: 27479060 | C68: 44586 | D68: Oliver GUGG (liquidateur de la succession de Siegfried Gugg) | E68: David HOULE, Mélanie SAVARD | F68: 3 387 707, 3 387 708 | G68: 260000 | I68: Lotbinière | J68: Saint-Antoine-de-Tilly | K68: 3351 Ch. Terre-Rouge Saint-Antoine-de-Tilly | L68: 46.639558 | M68: -71.494755 | N68: 22.3 | O68: oui | P68: Plane | Q68: 22.3 | S68: Feuillus | T68: 0.9 | U68: 0.1 | V68: 0.85 | AH68: =Table2[[#This Row],[Prix de vente ($)]]/Table2[[#This Row],[Superficie totale (ha)]] -> 11659.193 | AI68: =Bois!$G19/Bois!$AD19 -> #DIV/0!
A69: 26981505 | C69: 44589 | D69: GESTION DENIS DUBÉ INC | E69: 9165-8542 QUÉBEC INC | F69: 5547311 | G69: 125000 | I69: Les Basques | J69: Notre-Dame-des-neiges | K69: Rang 3e Oeust, Notre-Dame-des-neiges | L69: 48.085921 | M69: -69.142028 | N69: 61.27 | O69: oui | P69: Légère déclivité | Q69: 61.27 | R69: 0 | S69: mixte | T69: 0.5 | U69: 0.5 | AC69: 7.3 | AH69: =Table2[[#This Row],[Prix de vente ($)]]/Table2[[#This Row],[Superficie totale (ha)]] -> 2040.1502
A70: 27194809 | C70: 44591 | D70: Gervais GAGNÉ, Kate GAGNÉ | E70: Stéphane ROUSSELOT | F70: 5736802 | G70: 31000 | I70: La Haute-Côte-Nord | J70: Colombier | K70: Rue Principal, Colombier | L70: 48.860355 | M70: -68.863390 | N70: 21.08 | O70: non | P70: déclivité | Q70: 21.08 | S70: Resineux | T70: 0.2 | U70: 0.8 | AC70: 0 | AF70: pas en zone agricole | AH70: =Table2[[#This Row],[Prix de vente ($)]]/Table2[[#This Row],[Superficie totale (ha)]] -> 1470.5882
A71: 26991392 | C71: 44594 | D71: René BLAIS | E71: Dominique BLAIS, Martin CHAREST | F71: 3590294 | G71: 75000 | I71: Chaudière-Appalaches | J71: Notre-Dame-du-Sacré-Coeur-d'Issoudun | K71: Rang de la Plaine Notre-Dame-du-Sacré-Coeur-d'Issoudun | L71: 46.593480 | M71: -71.650882 | N71: 9.06 | O71: oui | P71: plane | Q71: 9.06 | S71: MF | T71: 0.6 | U71: 0.4 | AC71: 1.9 | AH71: =Table2[[#This Row],[Prix de vente ($)]]/Table2[[#This Row],[Superficie totale (ha)]] -> 8278.1457 | AI71: =G71/AD71 -> #DIV/0!
A72: 27000358 | C72: 44595 | D72: Pierre LÉTOURNEAU | E72: Michel BOURGOIN | F72: 6 479 924,5 150 328, 5 150 329, 5 150 330 | G72: 25000 | I72: Manicouagan | J72: Ragueneau | K72: rang 2e Chutes-aux_outardes, Ragueneau | L72: 49.120861 | M72: -68.442852 | N72: 37.5 | O72: non | P72: legère déclivité | Q72: 37.5 | R72: 0 | S72: Mixte | T72: 0.5 | U72: 0.5 | AC72: 0 | AF72: Zone humide (tourbière) | AH72: =Table2[[#This Row],[Prix de vente ($)]]/Table2[[#This Row],[Superficie totale (ha)]] -> 666.66667
A73: 27025667 | C73: 44609 | D73: Amélie PELLETIER | E73: ÉRABLIÈRE LA CANOPÉE INC François-Charles alias François GERMAIN | F73: 5 722 562, 5 405 624 | G73: 130000 | I73: Témiscouata | J73: Biencourt | K73: 8e Rang Ouest, Biencourt | L73: 47.939576 | M73: -68.583231 | N73: =5.71+36.24 -> 41.95 | O73: oui | P73: Déclivité | S73: Feuillus | T73: 0.6 | U73: 0.4 | V73: 0.75 | AF73: Accès favorable, chemin parcourant la terre. Rivière séparant les 2 lots | AH73: =Table2[[#This Row],[Prix de vente ($)]]/Table2[[#This Row],[Superficie totale (ha)]] -> 3098.9273
A74: 27031021 | C74: 44610 | D74: Donat PROVENCHER | E74: José AGUDELO, 9460-8858 QUEBEC INC, GESTION STELLOU INC. | F74: 4175729, 4175957 | G74: 209000 | I74: Les Chenaux | J74: Sainte-Anne de la Pérade | K74: Rang du Rapide Sud | L74: 46.627662 | M74: -72.165625 | N74: =26.49+26.08 -> 52.57 | O74: oui | P74: Irrégulière | Q74: 48.71 | R74: 3.86 | S74: R | T74: 0.2 | U74: 0.8 | AC74: 0 | AH74: =Table2[[#This Row],[Prix de vente ($)]]/Table2[[#This Row],[Superficie totale (ha)]] -> 3975.6515 | AI74: #DIV/0!
A75: 27046887 | C75: 44615 | D75: Rudy VANDERVALK KYLING | E75: 9458-8159 QUÉBEC INC (Stéphane Daudelin, Brigitte Ouellette) | F75: 3 980 311, 3 980 312 | G75: 350000 | I75: Brome-Missisquoi | J75: Dunham | K75: rue Principale, Dunham | L75: -72.827451 | M75: 45.086077 | N75: =10.28+22.88 -> 33.16 | O75: oui | P75: legere declivite | Q75: =10.28+22.88 -> 33.16 | R75: 0 | S75: Feuillus | T75: 0.9 | U75: 0.1 | V75: 90-100% | AC75: =19.5 -> 19.5 | AH75: =Table2[[#This Row],[Prix de vente ($)]]/Table2[[#This Row],[Superficie totale (ha)]] -> 10554.885
A76: 27050765 | C76: 44620 | D76: Christiane MASSE | E76: Pierre-Luc BOUCHARD, Audrey BOURGAULT | F76: 5426803 | G76: 20000 | I76: Kamouraska | J76: Mont-Carmel | K76: rang 5eme Ouest, Mont-Carmel | L76: 47.406826 | M76: -69.862191 | N76: 8.48 | O76: oui | P76: plane | Q76: 8.48 | R76: 0 | S76: Resineux | T76: 0.2 | U76: 0.8 | AC76: 0 | AF76: enclavé, servitude de passage | AH76: =Table2[[#This Row],[Prix de vente ($)]]/Table2[[#This Row],[Superficie totale (ha)]] -> 2358.4906
A77: 27054276 | C77: 44621 | D77: Lucien PARENT | E77: CANARDS ILLIMITÉS CANADA (Sébastien RIOUX) | F77: 5 239 261 | G77: 37500 | I77: Montérégie | J77: Le Haut-Richelieu | K77: rang Victoria, Saint-Georges-de- Clarenceville | L77: -73.222697 | M77: 45.073120 | N77: 9.31 | O77: oui | P77: Plane | Q77: 9.31 | R77: 0 | S77: Feuillus | T77: 1 | U77: 0 | V77: 70-79% | AC77: =1.3+0.8 -> 2.1 | AG77: 426105 (Autorisation), 334351 (Autorisation partielle) | AH77: =Table2[[#This Row],[Prix de vente ($)]]/Table2[[#This Row],[Superficie totale (ha)]] -> 4027.927
A78: 27155657 | C78: 44621 | D78: Thuribe BELZILE | E78: 9007-9690 QUÉBEC INC | F78: 5 840 308 | G78: 30000 | I78: Les Basques | J78: Saint-Clément | K78: Rang Saint-Isidore, Saint-Clément | L78: 47.957880 | M78: -69.086543 | N78: 14.55 | O78: oui | P78: Légère déclivité | Q78: 14.55 | R78: 0 | S78: Feuillus | T78: 0.6 | U78: 0.4 | AC78: 0 | AF78: Partie en zone inondable, pas de potentiel acéricole | AH78: =Table2[[#This Row],[Prix de vente ($)]]/Table2[[#This Row],[Superficie totale (ha)]] -> 2061.8557
A79: 27053802 | C79: 44621 | D79: LES ENTREPRISES FORESTIÈRES J.D. INC (Jacques DUGAS) | E79: Julien CAISSY, Jean-Philippe SAVOIE | F79: 3 887 736 et 3 887 314 | G79: 10000 | I79: Avignon | J79: Carleton-sur-Mer | K79: Route Saint-Louis Carleton-sur-Mer | L79: 48.142446 | M79: -66.242589 | N79: =18.55+5.51 -> 24.06 | O79: non | P79: Déclivité | Q79: =Bois!$N20 -> 41.51 | S79: Mixte | AF79: 2 lots séparés par la route Saint-Louis | AH79: =Table2[[#This Row],[Prix de vente ($)]]/Table2[[#This Row],[Superficie totale (ha)]] -> 415.6276 | AI79: =Bois!$G20/Bois!$AD20 -> 125
A80: 27234398 | C80: 44623 | D80: FERME MATHIEU ET PLANTE 2009 (SENC), | E80: GESTION J-P FORTIN INC | F80: 4339160 | G80: 240000 | I80: Les Appalaches | J80: Saint-Georges | K80: 369, 2e Rang, Saint-Georges | L80: 46.016742 | M80: -70.695962 | N80: 15.31 | O80: oui | P80: Légère déclivité | Q80: 15 | R80: 0 | S80: Feuillus | T80: 0.6 | U80: 0.4 | AC80: 6.6 | AF80: enclavé, presence de cabane à sucre, Contingent de 3420 LBS entailles présentement +/-1500 érables, possibilité de 1750 | AH80: =Table2[[#This Row],[Prix de vente ($)]]/Table2[[#This Row],[Superficie totale (ha)]] -> 15676.029
A81: 27064206 | C81: 44624 | D81: Guy MARTINEAU | E81: Yves BÉRUBÉ | F81: 5 675 550, 5 673 803 | G81: 53000 | I81: Les Basques | J81: Sainte-Françoise | K81: Rang 6e, Sainte-Françoise | L81: 48.088985 | M81: -68.989344 | N81: =20.54+12.89 -> 33.43 | O81: oui | P81: Légère déclivité | Q81: 33.43 | R81: 0 | S81: Feuillus | T81: 0.7 | U81: 0.3 | AC81: =2.1+5.6+8.1 -> 15.8 | AF81: enclavé, bon potentiel acéricole | AH81: =Table2[[#This Row],[Prix de vente ($)]]/Table2[[#This Row],[Superficie totale (ha)]] -> 1585.4023
A82: 27215754 | C82: 44629 | D82: Bertin CARON | E82: Rhéaume VEILLEUX | F82: 5839632 | G82: 25000 | I82: Les Basques | J82: Saint-Clément | K82: Rang Saint-Joseph, Saint-Clément | L82: 47.933347 | M82: -69.113946 | N82: 17.76 | O82: oui | P82: Légère déclivité | Q82: 17.76 | R82: 0 | S82: Feuillus | T82: 0.7 | U82: 0.3 | AC82: =1.9+0.1+1.6 -> 3.6 | AF82: enclavé | AH82: =Table2[[#This Row],[Prix de vente ($)]]/Table2[[#This Row],[Superficie totale (ha)]] -> 1407.6577
A83: 27078685 | C83: 44631 | D83: Hugues COUËT, Ginette PAQUET | E83: Chantal GAMACHE, Dany TREMBLAY | F83: 3831654 | G83: 24000 | I83: Portneuf | J83: Portneuf | K83: Portneuf | L83: 46.718696 | M83: -71.601644 | N83: 4.47 | O83: oui | P83: Plane | Q83: 4.47 | S83: Mixte | AF83: Passage d'un gazoduc | AG83: 422523 (aménagement zone travaux, entretien gazoduc) | AH83: =Table2[[#This Row],[Prix de vente ($)]]/Table2[[#This Row],[Superficie totale (ha)]] -> 5369.1275 | AI83: =Bois!$G21/Bois!$AD21 -> #DIV/0!
A84: 27077849 | C84: 44631 | D84: Denis JOLY | E84: France PAPINEAU, Lucie PAPINEAU | F84: 5 091 761 | G84: 80000 | I84: antoine-labelle | J84: Ferme-neuve | K84: 3e rang de Pope | L84: 46.675664 | M84: -75.504957 | N84: 43.89 | O84: non | P84: déclivité importante | Q84: 43.89 | S84: feuillus | T84: 1 | U84: 0 | V84: 0.7 | AF84: grand potentiel acéricole, bonne essence de bois sur le lot | AH84: =Table2[[#This Row],[Prix de vente ($)]]/Table2[[#This Row],[Superficie totale (ha)]] -> 1822.7387
B85: 17965296 | C85: 44632 | F85: 5 347 386, 5 347 388, 5 347 389 | G85: 715000 | I85: Chaudière-Appalaches | J85: Saint-Adalbert | K85: 251 Route 204 O. Saint-Adalbert | L85: 46.839400 | M85: -69.941432 | N85: =(5851300.09/10.7639)/10000 -> 54.360409 | O85: oui | P85: pente | Q85: =N85 -> 54.360409 | AC85: 29 | AD85: 9500 | AF85: Séparateur osmose 900 gallons Dominion, tubulure 4 ans, pompe vaccum Delaval 78 avec récupérateur, dumper Bernard 220, réservoir 8000 gallons. | AH85: =Table2[[#This Row],[Prix de vente ($)]]/Table2[[#This Row],[Superficie totale (ha)]] -> 13152.955 | AI85: =G85/AD85 -> 75.263158
B86: 20696619 | C86: 44636 | F86: 3644308 | G86: 131000 | I86: Lévis | J86: Lévis | K86: Route St-André Lévis (Les Chutes-de-la-Chaudière-Ouest) | L86: 46.643314 | M86: -71.243766 | N86: 13.22 | O86: oui | P86: plane | Q86: =N86-R86 -> 10.02 | R86: =1.9+1.3 -> 3.2 | S86: Feuillus | T86: 0.8 | U86: 0.2 | AH86: =Table2[[#This Row],[Prix de vente ($)]]/Table2[[#This Row],[Superficie totale (ha)]] -> 9909.2284 | AI86: #DIV/0!
A87: 27095054 | C87: 44638 | D87: Dany DUBÉ | E87: Francis DUBÉ DAOUST | F87: 3887146 | G87: 5200 | I87: Avignon | J87: Carleton-sur-Mer | K87: Rang 2 Nouvelle Carleton-sur-Mer | L87: 48.134310 | M87: -66.245558 | N87: 6.41 | O87: non | P87: Forte déclivité | Q87: 6.41 | S87: Mixte | AH87: =Table2[[#This Row],[Prix de vente ($)]]/Table2[[#This Row],[Superficie totale (ha)]] -> 811.23245 | AI87: =Bois!$G22/Bois!$AD22 -> #DIV/0!
A88: 27121061 | C88: 44650 | D88: Claude BRETON, Julie POTVIN | E88: Bruno SAUVAGEAU, Marie-Hélène ROBERGE | F88: 5401062 | G88: 130000 | I88: Charlevoix-Est | J88: La Malbaie | K88: Chemin de Port-au-Persil, La Malbaie | L88: 47.785870 | M88: -69.928550 | N88: 30.8 | O88: non | P88: déclivité | Q88: 30.8 | R88: 0 | S88: Mixte | T88: 0.5 | U88: 0.5 | AC88: 3.2 | AF88: resineux, potentiel acéricole | AH88: =Table2[[#This Row],[Prix de vente ($)]]/Table2[[#This Row],[Superficie totale (ha)]] -> 4220.7792
A89: 27286107 | C89: 44656 | D89: SOLIFOR CHARLEVOIX-SAGUENAY, SOCIÉTÉ EN COMMANDITE | E89: Guy BÉLISLE | F89: 5 400 733, 5 400 732, 5 400 734 | G89: 150000 | I89: Charlevoix-Est | J89: La Malbaie | K89: Rang Sainte-Anne, La Malbaie | L89: 47.792086 | M89: -69.963342 | N89: 63.68 | O89: non | P89: legère déclivité | Q89: 56.58 | R89: 0 | S89: Resineux | T89: 0.3 | U89: 0.7 | AC89: 6.9 | AF89: resineux, potentiel acéricole | AH89: =Table2[[#This Row],[Prix de vente ($)]]/Table2[[#This Row],[Superficie totale (ha)]] -> 2355.5276
A90: 27169372 | C90: 44670 | D90: Gérard HAMMOND | E90: Abel OUELLET | F90: 4476738 | G90: 44000 | I90: Les Basques | J90: Saint-Mathieu-de-Rioux | K90: 4è Rang Est, Saint-Mathieu-de-Rioux | L90: 48.190119 | M90: -68.937692 | N90: 19.84 | O90: oui | P90: Légère déclivité | Q90: 19.84 | R90: 0 | S90: Resineux | T90: 0.3 | U90: 0.7 | AC90: 1.8 | AF90: Resineux, peu de potentiel acéricole | AH90: =Table2[[#This Row],[Prix de vente ($)]]/Table2[[#This Row],[Superficie totale (ha)]] -> 2217.7419
A91: 27184491 | C91: 44677 | D91: Martin SIMARD | E91: 9126-7815 QUÉBEC INC Gervais BOURQUE, Vicky BELZILE | F91: 6483749 | G91: 84000 | I91: Les Basques | J91: Saint-Guy | K91: 4e rang, à Saint-Guy | L91: 48.014836 | M91: -68.790957 | N91: 18.38 | O91: non | P91: Déclivité | S91: Feuillus | T91: 1 | U91: 0 | V91: 0.85 | AC91: 18.38 | AF91: Accès par chemin privé. Proximité lac de Saint-Guy | AH91: =Table2[[#This Row],[Prix de vente ($)]]/Table2[[#This Row],[Superficie totale (ha)]] -> 4570.185
A92: 27197623 | C92: 44680 | D92: Joëlle CROTEAU | E92: Martine BOUCHER, Alain CHAREST | F92: 3584542 | G92: 21000 | I92: Lotbinière | J92: Saint-Apollinaire | K92: Route de la Carrière Saint-Apollinaire | L92: 46.565892 | M92: -71.543220 | N92: 3.97 | O92: oui | P92: Plane | Q92: =Bois!$N23 -> 8.44 | S92: Mixte | T92: 0.5 | U92: 0.5 | V92: 0.85 | AH92: =Table2[[#This Row],[Prix de vente ($)]]/Table2[[#This Row],[Superficie totale (ha)]] -> 5289.6725 | AI92: =Bois!$G23/Bois!$AD23 -> #DIV/0!
A93: 27202665 | C93: 44680 | D93: 9352-8347 QUEBEC INC. | E93: Sophie CORMIER-RONDEAU, Charles GOULET | F93: 3926497, 4176002 | G93: 69000 | I93: Portneuf | J93: Deschambault-Grondines | K93: Rang d'Orvilliers | L93: 46.602175 | M93: -72.124923 | N93: =2.34+4.34 -> 6.68 | O93: oui | P93: Irrégulière | Q93: 6.68 | R93: 0 | S93: Mixte | T93: 0.5 | U93: 0.5 | AC93: 0.8 | AH93: =Table2[[#This Row],[Prix de vente ($)]]/Table2[[#This Row],[Superficie totale (ha)]] -> 10329.341 | AI93: #DIV/0!
A94: 27202358 | C94: 44683 | D94: Carl DESBIENS | E94: GESTION JACKY SANTERRE INC. | F94: 5 759 753 | G94: 48000 | I94: Manicouagan | J94: Ragueneau | K94: 2ieme rang,Ragueneau | L94: 49.093784 | M94: -68.461674 | N94: 38.15 | O94: oui | P94: legere declivite | Q94: 38,15 | R94: 0 | S94: résineux | T94: 0.8 | U94: 0.2 | AC94: 0 | AH94: =Table2[[#This Row],[Prix de vente ($)]]/Table2[[#This Row],[Superficie totale (ha)]] -> 1258.1913
A95: 27226977 | C95: 44692 | D95: Raymonde BLANEY | E95: FERME DENIS ET LOUISE DION SENC | F95: 6496748 | G95: 380000 | I95: La Nouvelle Beauce | J95: Saint-narcisse-de-Beaurivage | K95: 209 Rang ST-Anne | L95: 46.465609 | M95: -71.297349 | N95: 32.06 | O95: oui | P95: Plane | Q95: 15.7 | R95: 16.36 | S95: Feuillus | T95: 0.6 | U95: 0.4 | V95: 0.7 | AH95: =Table2[[#This Row],[Prix de vente ($)]]/Table2[[#This Row],[Superficie totale (ha)]] -> 11852.776
A96: 27234752 | C96: 44694 | D96: FERME JOSEPH AIMÉ BLAIS INC | E96: Jean-François ROY, Karine BLAIS | F96: 3475645 | G96: 25000 | I96: Montmagny | J96: Saint- François-de-la-Rivière-du-Sud | K96: chemin des Prairies Saint- François-de-la-Rivière-du-Sud | L96: 46.852547 | M96: -70.662231 | N96: 6.24 | O96: oui | P96: Légère déclivité | Q96: =N96 -> 6.24 | S96: Feuillus | T96: 0.7 | U96: 0.3 | V96: 0.8 | AC96: 0 | AF96: Enclavé, servitude de passage | AH96: =Table2[[#This Row],[Prix de vente ($)]]/Table2[[#This Row],[Superficie totale (ha)]] -> 4006.4103 | AI96: #DIV/0!
A97: 27247829 | C97: 44699 | D97: Jean-Pierre SYLVAIN, Michel SYLVAIN | E97: BOISÉ PELLETIER (2022) S.E.N.C | F97: 5179301 | G97: 225000 | I97: Les Etchemins | J97: Saint-Louis-de-Gonzague | K97: 11 e rang, Saint-Louis-de-Gonzague | L97: 46.229621 | M97: -70.342551 | N97: 39.88 | O97: oui | P97: Légère déclivité | Q97: 39.88 | R97: 0 | S97: Mixte | T97: 0.5 | U97: 0.5 | AC97: 10 | AF97: 1 100 entailles | AH97: =Table2[[#This Row],[Prix de vente ($)]]/Table2[[#This Row],[Superficie totale (ha)]] -> 5641.9258
A98: 27259570 | C98: 44701 | D98: Marc BEAUMONT | E98: Jean-Charles LEPAGE | F98: 3 055 781, 3 055 819 | G98: 30000 | I98: Québec | J98: Saint-Augustin-de-Desmaures | K98: chemin du Cabouron, Saint-Augustin-de-Desmaures | L98: 46.748576 | M98: -71.551138 | N98: =2.61+1.76 -> 4.37 | O98: oui | P98: Plane | Q98: 4.37 | S98: Mixte (dominance résineux) | T98: 0.34 | U98: 0.66 | V98: 0.7 | AF98: Traversé par 2 cours d'eau, 2 lots séparés par une voie ferrée, Accès chemin | AH98: =Table2[[#This Row],[Prix de vente ($)]]/Table2[[#This Row],[Superficie totale (ha)]] -> 6864.9886 | AI98: =Bois!$G25/Bois!$AD25 -> #DIV/0!
A99: 27550768 | C99: 44701 | D99: Sébastien RAJOTTE | E99: Jean-Philippe GAGNON SAVARD, Jacob LECLERC | F99: 5883952 | G99: 85000 | I99: Nicolet-Yamaska | J99: Saint-Zéphirin-de-Courval | K99: rang Saint-Louis Saint-Zéphirin-de-Courval | L99: 46.046453 | M99: -72.581966 | N99: 10.53 | O99: oui | P99: Plane | Q99: =Bois!$N24 -> 25.96 | S99: Mixte | T99: 0.5 | U99: 0.5 | AH99: =Table2[[#This Row],[Prix de vente ($)]]/Table2[[#This Row],[Superficie totale (ha)]] -> 8072.1747 | AI99: =Bois!$G24/Bois!$AD24 -> #DIV/0!
A100: 26929308 | C100: 44703 | D100: Langis GAUDREAU | E100: Jonathan GROULX | F100: 5943794 | G100: 40000 | I100: Papineau | J100: Ripon | K100: Montée Rochon, Ripon | L100: 45.752149 | M100: -75.175581 | N100: 21.09 | O100: non | P100: déclivité | Q100: 21.09 | R100: 0 | S100: Feuillus | T100: 0.85 | U100: 0.15 | AC100: 5.8 | AF100: enclavé | AH100: =Table2[[#This Row],[Prix de vente ($)]]/Table2[[#This Row],[Superficie totale (ha)]] -> 1896.6335
...

Sheet Terre
A1: No d'enr. | B1: SIA | C1: Date de l'acte ou de l'avant contrat | D1: Vendeur | E1: Acheteur | F1: Lots | G1: Prixdevente($) | H1: Prix de vente redressé au temps ($) | I1: MRC | J1: Ville/Municipalité | K1: Adresse complète | L1: Latitude | M1: Longitude | N1: Superficie totale (ha) | O1: Zone agricole (CPTAQ) | P1: Topographie | Q1: Classe de sol dominante | R1: Sous-classe dominante | S1: Superficie cultivée (ha) | T1: Source superficie cultivée | U1: Superficie drainée (ha) | V1: Source superficie drainée | W1: Type de sol | X1: Type de culture | Y1: Superficie boisée (ha) | Z1: Superficie plantation | AA1: Superficie terrain résidentiel (m²) | AB1: Droit acquis | AC1: Maison(s) | AD1: Valeur contributive maison(s) + terrain ($) | AE1: Source valeur constributive maison(s) + terrain ($) | AF1: Bâtiments agricoles | AG1: Valeur contributive bâtiments agricoles ($) | AH1: Source valeur constributive bâtiments agricoles | AI1: Autres inclusions | AJ1: Valeur autres inclusions ($) | AK1: Observations | AL1: Décisions CPTAQ | AM1: Taux unitaire global ($/ha)
A2: 22309676 | C2: 42507 | D2: Réjean Lemire, Claude Lemire | E2: Michel Proulx | F2: 5433069 | G2: 36000 | I2: Nicolet-Yamaska | J2: Baie-du-Febvre | K2: Route Marie-Victorin Baie-du-Febvre | L2: 46.154336 | M2: -72.706115 | N2: 6.25 | O2: Oui | P2: Plane | Q2: 4 | R2: FW | S2: =4.7+0.8 -> 5.5 | T2: FADQ | AK2: Potentiel acéricole dans les terrains riverrains,(érables rouges) | AM2: =G2/N2 -> 5760
A3: 22859457 | C3: 42696 | D3: Ovide Savard | E3: La Ferme des Quatre-Temps Inc (Marguerite Tremblay) | F3: 5401041 | G3: 323000 | I3: Charlevoix-Est | J3: La Malbaie | K3: Boulevard Malcolm-Fraser La Malbaie | L3: 47.797659 | M3: -69.934839 | N3: =524558.875/10000 -> 52.455888 | O3: oui | P3: Légère pente | Q3: 3 | R3: P | S3: =1+0.7+1.8+3.2+1.8+0.8+3.4 -> 12.7 | T3: FADQ | Y3: =Terre!$N34-Terre!$S34 -> 10.27 | AK3: bande de terre située entre deux terres qui étais probablement manquante pour la compagnie, non drainée | AM3: =G3/N3 -> 6157.5548
A4: 23128070 | C4: 42791 | D4: FERME MARTEL 1999 INC (Jean-Jacques MARTEL) | E4: LES BELLES RÉCOLTES DE CHARLEVOIX INC (Stéphane DUFOUR) | F4: 5 400 604, 3 560 775, 5 063 796, 5 400 619 | G4: 430000 | I4: Charlevoix-Est | J4: La Malbaie | K4: chemin des Loisirs et chemin de la Vallée La Malbaie | L4: 47.688972 | M4: -70.171369 | N4: 70.1 | O4: oui | P4: Légère pente | Q4: 3 | R4: FMT | S4: =48.4+9 -> 57.4 | T4: FADQ | Y4: =6.4+0.2 -> 6.6 | AK4: Vente de 2 terres, en face de la rivière, non drainées,voisin d'une propriété acéricole | AM4: =G4/N4 -> 6134.0942
A5: 24059816 | B5: 12936685 | C5: 43273 | D5: Camille TREMBLAY | E5: Denis LAPOINTE | F5: 5439978 | G5: 60000 | I5: Charlevoix-Est | J5: Saint-Irénée | K5: chemin des Bains Saint-Irénée | L5: 47.533781 | M5: -70.225115 | N5: =1391568.5/10.7639/10000 -> 12.928107 | O5: oui | P5: Relativement plane | Q5: 5 | R5: PT | S5: =Terre!$N62-Terre!$Y62 -> 94.1 | T5: Mesures Demeter | Y5: 3.1 | AK5: vente à un prix élevé à la municipalité | AM5: =G5/N5 -> 4641.0507
A6: 24386780 | C6: 43490 | D6: La BLEUETIÈRE BEAULIEU INC. | E6: 9161-2754 QUÉBEC INC. | F6: 5 219 647 | G6: 100000 | I6: Manicouagan | J6: pointe-lebel | K6: Route de l'aréoport, Pointe-Lebel | L6: 49.140934 | M6: -68.205762 | N6: 15 | O6: oui | P6: plane | Q6: 4 | R6: FD | S6: 11.4 | T6: FADQ | U6: 0 | V6: infosol | Y6: 0 | AK6: très grand terrains boisée combiné avec terre agricole. FADQ médiocre sur terre donc certaine mesures sont faites a la main. | AM6: =G6/N6 -> 6666.6667
A7: 24495986 | C7: 43552 | D7: ANDRÉ LEMAIRE INC | E7: CULTURES ROUSSEAU INC (Paul ROUSSEAU) | F7: 5743147, 5745024, 5 743 148, 5433045, 5434246, 5434247, 5434264, 5 433 041 | G7: 1992000 | I7: Nicolet-Yamaska | J7: Baie-du-Febvre | K7: Rg du Petit-Bois Baie-du-Febvre | L7: 46.112650 | M7: -72.773585 | N7: =(137446.3+168074.1+2208+183126+24253.2+137398.2+60183.3+10222.5)/10000 -> 72.29116 | O7: oui | P7: Plane | Q7: 3 | R7: FW | S7: =6.7+17+45.5+13.3-12.1 -> 70.4 | T7: FADQ | U7: =16.81+18.31+13.74 -> 48.86 | AK7: non drainée | AM7: =G7/N7 -> 27555.236
A8: 24718742 | C8: 43643 | D8: Mario GAMELIN | E8: Marie-Philippe FRENETTE DANEAU | F8: 5744548 | G8: 50000 | I8: Nicolet-Yamaska | J8: Pierreville | K8: chemin du Marais-Blazon Pierreville | L8: 46.109543 | M8: -72.900294 | N8: 6.06 | O8: oui | P8: Plane | Q8: 3 | R8: FW | S8: 5.5 | T8: FADQ | AK8: Non drainé, zone agricole mais non délimité par la FADQ | AM8: =G8/N8 -> 8250.8251
A9: 25326259 | C9: 43724 | D9: FERME PROMAS INC (Martine Massé) | E9: FERME MICHDALE (Michael Leduc) | F9: 5 691 498, 5 691 427, 5 691 439 | G9: 621500 | I9: Les Appalaches | J9: Saint-Julien | K9: 2e Rang Ouest Saint-Julien | L9: 46.046685 | M9: -71.567924 | N9: =10.59+12.89+55.29 -> 78.77 | O9: Oui | P9: Plane | Q9: 7 | R9: PT | S9: =10.59+9.49+24.99 -> 45.07 | T9: Mesures Demeter | U9: 0 | X9: Prairie | Y9: =3.4+30.3 -> 33.7 | AF9: 3 hangars, fosse | AG9: =102700+36000 -> 138700 | AH9: Acte | AI9: Équipements, matériel | AJ9: =60800+22000 -> 82800 | AK9: En partie mineure de classe 5, droit d'usage conféré au vendeur (superficie négligeable) | AM9: =G9/N9 -> 7890.0597
A10: 25161637 | C10: 43846 | D10: Pavage C.S.F. Inc. | E10: 9122-3388 Quebec Inc. | F10: 5456717 | G10: 653 175 | J10: Notre-Dame-De-L'Ile-Perrot | K10: 0 | AJ10: Petite bois, non CPTAQ | AM10: =G10/N10 -> #VALUE!
A11: 25160283 | C11: 43850 | D11: 2858967 CANADA INC Claude DESROCHERS | E11: 9391-5619 QUÉBEC INC Pierre COUILLARD | F11: 6 312 083, 5 310 276 | G11: 1500000 | J11: Saint-Marc-sur-Richelieu | K11: Rue Richelieu, Saint-Marc-sur-Richelieu | N11: =0.24+36.65 -> 36.89 | O11: Oui | P11: plane | Q11: 4 | R11: FW | S11: =10.7+18.8 -> 29.5 | U11: =Table3[[#This Row],[Superficie cultivée (ha)]] -> 29.5 | Y11: 5 | AF11: 1 hangar (mauvais état) | AM11: =G11/N11 -> 40661.426
A12: 25184870 | C12: 43859 | D12: Sylvain TESSIER | E12: Hughes LEBOEUF | F12: 4 175 797, 4 176 629 | G12: 150000 | I12: Les Chenaux | J12: Sainte-Anne de la Pérade | K12: Sainte-Anne de la Pérade | L12: 46.626915 | M12: -72.228613 | N12: =8.39+8.46 -> 16.85 | O12: oui | P12: Plane | Q12: 3 | R12: W | S12: =4.6+6.2 -> 10.8 | T12: FADQ | Y12: 5.7 | AK12: non drainé | AM12: =G12/N12 -> 8902.0772
A13: 25184865 | C13: 43859 | D13: FERME BOIS-DU-MERLE S.E.N.C. (Marcel et Martin Juneau) | E13: FERME RAINIER ET ASSOCIÉS S.E.N.C (Christian et Mario Germain) | F13: 4175461 | G13: 500000 | I13: Les Chenaux | J13: Sainte-Anne de la Pérade | K13: Sainte-Anne de la Pérade | L13: 46.564578 | M13: -72.241371 | N13: 27.69 | O13: oui | P13: Plane | Q13: 3 | R13: W | S13: =9.1+7.2+9.9 -> 26.2 | T13: FADQ | AK13: enclavé, servitude de passage | AM13: =G13/N13 -> 18057.06
A14: 25205856 | C14: 43873 | D14: Jocelyn GIROUARD | E14: FERME GHISLAIN CLOUTIER INC Ghislain CLOUTIER | F14: 2706581 | G14: 400000 | I14: Les Maskoutains | J14: St-Barnabé-Sud | K14: Rang St-Amable, St-Barnabé-Sud | L14: 45.759554 | M14: -72.904675 | N14: 7.69 | O14: Oui | P14: plane | Q14: 2 | R14: W | S14: 7.3 | AM14: =G14/N14 -> 52015.605
A15: 25225318 | C15: 43882 | D15: FERME P. & M. CHAMPAGNE INC | E15: FERME TERREBONNE INC | F15: 2 849 451, 2 849 450, 3 283 310 | G15: 309500 | I15: Lévis | J15: Lévis | K15: chemin petit St Jean, Lévis | L15: 46.671480 | M15: -71.318910 | N15: 39.33 | O15: oui | P15: Plane | Q15: 4 | R15: WP | S15: 23.6 | T15: FADQ | Y15: 13.4 | AK15: non drainé | AM15: =G15/N15 -> 7869.311
A16: 25270667 | C16: 43907 | D16: LE SANCTUAIRE DE LA VALLÉE DU RICHELIEU INC. André SIMONEAU | E16: 9342-4497 QUÉBEC INC Dave VILLENEUVE | F16: 5132029 | G16: 750000 | I16: La-Vallée-du-Richelieu | J16: St-Mathieu-de-Beloeil | K16: Rue Bernard-PilonSt-Mathieu-de-Beloeil | L16: 45.581457 | M16: -73.277008 | N16: 2.82 | O16: Oui | P16: plane | Q16: 2 | R16: W | S16: 2.6 | AK16: Solde du prix de 550 000 $ au plus tard soit au moment du dézonage (agricole) soit au 13 mars 2023 | AL16: 335956 | AM16: =G16/N16 -> 265957.45
A17: 26079068 | C17: 43911 | D17: Claude CHÉNIER | E17: FERME NINON INC | F17: 4 652 183, 6 370 298 | G17: 480000 | I17: Papineau | J17: Lochaber-Partie-Ouest | K17: Rang 4e, Lochaber-Partie-Ouest | L17: 45.591390 | M17: -75.287421 | N17: 57.67 | O17: oui | P17: Legere pente | Q17: 3 | R17: F | S17: 31.9 | T17: FADQ | U17: 0 | V17: infosol | Y17: 24.25 | AK17: non drainé | AM17: =G17/N17 -> 8323.2183
A18: 25344540 | C18: 43950 | D18: FERME DIANE S.E.N.C. Diane PHANEUF et Patrick LAVALLÉE | E18: Lison BÉDARD | F18: 2708676 | G18: 190000 | J18: Saint-Jude | K18: Rang des Quarante-huit, Saint-Jude | L18: 45.808984 | M18: -72.967530 | N18: 13.65 | O18: Oui | P18: plane | Q18: 2 | R18: X | S18: 6.9 | Y18: 4.5 | AM18: =G18/N18 -> 13919.414
A19: 25369557 | C19: 43963 | D19: Jocelyn RICHER | E19: SOCIÉTÉ CBCA SNC Chrétien ARCHAMBAULT | F19: 3698783 | G19: 300000 | J19: Saint-Denis-sur-Richelieu | K19: 3e rang des Moulins est, Saint-Denis-sur-Richelieu | L19: 45.776104 | M19: -73.123560 | N19: 5.13 | O19: Oui | P19: plane | Q19: 2 | R19: W | S19: 4.8 | U19: =Table3[[#This Row],[Superficie cultivée (ha)]] -> 4.8 | AM19: =G19/N19 -> 58479.532
A20: 25396662 | C20: 43976 | D20: Marie-Joseph PIGEON | E20: FERME VIAGRICO INC Bruno VIENS et Jessica BÉRUBÉ | F20: 5 310 296, 5 312 004, 5 312 098 | G20: 1200000 | J20: Saint-Marc-sur-Richelieu | L20: 45.731186 | M20: -73.202806 | N20: =26.12+16.49+0.09 -> 42.7 | O20: Oui | P20: plane | Q20: 2 et 4 | R20: W | S20: =12.8+2.6+6+7.8 -> 29.2 | Y20: 5.5 | AM20: =G20/N20 -> 28103.044
A21: 25451290 | C21: 43994 | D21: Ghyslain PROVOST, JARDINS PROVOST INC | E21: 9417-9082 QUÉBEC INC Serge ARCHAMBAULT | F21: 1 912 197, 1 912 199, 1 912 733, 1 912 952, 1 912 953 | G21: 1175000 | I21: Marguerite-D'Youville | J21: Boucherville | K21: 1381, chemin Général-Vanier à Boucherville | N21: =6.05+6.75+0.43+7.68+2.59 -> 23.5 | Q21: 2 | R21: W | S21: 16.6 | AF21: Kiosque de vente, hangar 90'x50' | AK21: le tracteur John Deer modèle 3320, 2011, dont le numéro d’identification est le 1LV3320HKBH711054; et, - un camion GMC modèle Savana, 2002, dont le numéro d’identification est le 1GTFG25M921240884.un semoir à blé d’inde; - un vibroculteur; - un set de roulettes; et, - un véhicule de Marque Dodge, modèle RMV, année 2002, dont le numéro d’identification est le 2B7JB21YX2K132098 | AM21: =G21/N21 -> 50000
A22: 26427913 | C22: 44003 | D22: FERME HÉLÉNOISE INC | E22: FERME BIENVU & FILS INC. | F22: 1 956 966, 1 959 926 | G22: 3385000 | I22: les Maskoutains | J22: Sainte-Hélène-de-Bagot | K22: 2e rang Sainte-Hélène-de-Bagot | L22: 45.714528 | M22: -72.758705 | N22: 70.91 | O22: OUI | P22: Plane | Q22: 3 | R22: FW | S22: 63.5 | T22: FADQ | U22: 63.5 | V22: infosol | Y22: 3.1 | AA22: 2218.5 | AC22: 1 | AF22: Bâtiment d’élevage, garage, Silos et Fosse à lisier | AK22: Drainé | AM22: =G22/N22 -> 47736.567
A23: 25541105 | C23: 44027 | D23: FERME BAZINET ET FILS INC | E23: Martin BRODEUR-CHOQUETTE | F23: 3407614 | G23: 538594 | I23: La-Vallée-du-Richelieu | J23: Saint-Charles-sur-Richelieu | L23: 45.681639 | M23: -73.171122 | N23: 12.52 | O23: Oui | P23: plane | Q23: 2 | R23: W | S23: 11.6 | U23: =Table3[[#This Row],[Superficie cultivée (ha)]] -> 11.6 | AM23: =G23/N23 -> 43018.69
A24: 25629542 | B24: 22138106 | C24: 44034 | D24: Martin LAPOINTE, Manon BOUCHARD | E24: Pierre PAQUET | F24: 5438957 | G24: 300000 | I24: Charlevoix | J24: Les Éboulements | K24: 2490, Route du Fleuve Les Éboulements | L24: 47.479265 | M24: -70.309319 | N24: =502738.98/10.7639/10000 -> 4.6706025 | O24: oui | P24: Plane | Q24: 3 | R24: P | S24: =Terre!$N38-Terre!#REF! -> #REF! | T24: Mesures Demeter | AF24: Bâtiment de 2006 | AG24: 140000 | AI24: Tracteur et équipements aratoires | AJ24: 30000 | AK24: Presence de bâtiment | AM24: =G24/N24 -> 64231.542
A25: 25713777 | C25: 44057 | D25: Steeve POULIN | E25: FERME FAMILLE ST-HILAIRE S.E.N.C. | F25: 4340477 | G25: 40000 | I25: Robert-Cliche | J25: Saint-Odilon-de-Cranbourne | K25: 8e Rang Ouest Saint-Odilon-de-Cranbourne | L25: 46.305958 | M25: -70.687122 | N25: 5.61 | O25: Oui | P25: Plane | Q25: 5 | R25: PW | S25: 3.8 | T25: Mesures Demeter | V25: infosol | X25: Maïs fourrager | Y25: 1.8 | AK25: Drainée | AM25: =G25/N25 -> 7130.1248
A26: 25 640 643 | C26: 44070 | D26: Pachanos Margaret Rose | E26: Venne Matthieu | F26: 5 372 421, 5 373 988 | G26: 40000 | I26: La Vallé-de-l'Or | J26: Sanneterre | K26: ch Croinor | L26: 48.348934 | M26: -77.26329 | N26: 12.96 | O26: oui/non | P26: Plane | Q26: 4 | R26: TD | S26: 5.4 | T26: Mesures aériennes | W26: Argileux | Y26: 6.9 | AK26: La terre semble plus cultivé, la friche repousse | AM26: =G26/N26 -> 3086.4198
A27: 25662799 | C27: 44078 | F27: 6367545 | G27: 240000 | I27: Témiscouata | J27: Témiscouata-sur-le-Lac | K27: rue Commerciale Nord, Témiscouata-sur-le-Lac | L27: 47.652577 | M27: -68.835944 | N27: 48.89 | O27: oui | P27: Légère pente | Q27: 3 | R27: tp | S27: =8.5+0.6+2.8 -> 11.9 | T27: fadq | Y27: 34 | AM27: =G27/N27 -> 4908.9793
A28: 25700380 | C28: 44096 | D28: Yvon DAUPHINAIS | E28: 9320-3792 Québec Inc Mohamed-Elyès JOUINI | F28: 2 600 783, 2 601 574 | G28: 410000 | I28: La-Vallée-du-Richelieu | J28: Carignan | K28: Chemin Bellerive, Carignan | L28: 45.421964 | M28: -73.367582 | N28: =20.25+12.54 -> 32.79 | O28: Oui | P28: plane | Q28: 2 | R28: W | S28: =5.8+0.08+3.9+0.7+1.5 -> 11.98 | Y28: 13.2 | AK28: à l’intérieur d’une zone d’inondation de grand courant (récurrence 0-20 ans) et faible courant (récurrence 20-100 ans) | AM28: =G28/N28 -> 12503.812
A29: 25934008 | C29: 44106 | D29: LES GRAINS DE LA MAURICIE INC (Roger GAUTHIER, Jacqueline HÉBERT) | E29: Vincent COULOMBE | F29: 4 175 743, 4 175 753, 4 306 126, 5 618 790, 5 618 345, 5 618 903, 5 619 121 | G29: 1070000 | I29: Les Chenaux | J29: Saint-Prosper-de-Champlain | K29: Rang Sainte- Elisabeth Saint-Prosper-de-Champlain | L29: 46.621800 | M29: -72.249023 | N29: =7.74+13.97+1.57+5.89+14.82+4.57+23.17 -> 71.73 | O29: oui | P29: Plane | Q29: 2 | R29: W | S29: =7.74+12.9+0.8+3.6+12.6+4.3+5.7+7.3 -> 54.94 | T29: FADQ | Y29: =0.8+0.8+1+9.5 -> 12.1 | AM29: =G29/N29 -> 14917.05
A30: 27123066 | C30: 44116 | D30: Laval RICHARD, Margaret POULIN | E30: FERME PIAL INC (Mathieu CHÉNARD) | F30: 6 422 974, 5 170 539 | G30: 200000 | I30: Kamouraska | J30: Saint-Josephde- Kamouraska | K30: 4e Rang Est St-Joseph-de-Kamouraska | L30: 47.627697 | M30: -69.640950 | N30: =(186034.297+110432.203)/10000 -> 29.64665 | O30: oui | P30: Relativement plane | Q30: 4 | R30: FM | S30: =0.2+8.5+3.5+2.6+1.8 -> 16.6 | T30: FADQ | Y30: =Terre!$N66-Terre!$S66 -> 0.98 | AM30: =G30/N30 -> 6746.1248
A31: 25764750 | C31: 44119 | D31: André LAMBERT | E31: FERME BÉLANGEOISE INC | F31: 1 964 910, 3 387 636 | G31: 100000 | I31: Lévis | J31: Lévis | K31: chemin Filteau, Lévis | L31: 46.646697 | M31: -71.441468 | N31: 12.71 | O31: oui | P31: Plane | Q31: 4 | R31: WP | S31: 7.2 | T31: FADQ | Y31: 3.3 | AL31: 441527 (usage résidentiel, exclus de la vente) | AM31: =G31/N31 -> 7867.8206
A32: 25767842 | C32: 44120 | D32: Serge MACHABEE, Marcel CHARTRAND, Isabelle CHARTRAND, Patrice CHARTRAND | E32: SAFRAN AGRICULTURE S.E.N.C. Sasan BAYAT MAKOU, Fereidoun HARANDIAN, Nader SADEGHI et Ramin KHODAYARI | F32: 6185182 | G32: 1800000 | J32: Longueuil | K32: Grande Alle, Longueuil | L32: 45.445508 | M32: -73.397179 | N32: 52.83 | O32: Oui | P32: plane | Q32: 2 | R32: W | S32: =2.3+2.1+2.9+3.8+6.4+2.9+6.6+2.4+3.4 -> 32.8 | Y32: 15 | AM32: =G32/N32 -> 34071.55
A33: 26442237 | C33: 44123 | D33: Alain BERNIER | E33: FERME ELAMARC INC. | F33: 2 819 306, 6 434 818, 6 434 819 | G33: 525000 | I33: Bellechasse | J33: Saint-Charles-de- Bellechasse | K33: rang Sud-Ouest | L33: 46.728979 | M33: -70.951184 | N33: 29.93 | O33: Oui | P33: Plane | Q33: 3 | R33: W | S33: 21.2 | T33: Déméter et FADQ | U33: Oui | V33: Infosols | X33: Orge, foin | AK33: Valeur inclusions selon acte | AM33: =G33/N33 -> 17540.929
A34: 25847015 | C34: 44148 | D34: Hélène BERGERON | E34: Samuel BEAURIVAGE | F34: 2 245 214, 2 332 167, 5 663 807 | G34: 262500 | I34: Lévis | J34: Lévis | K34: route Marie-Victorin, Lévis | L34: 46.680184 | M34: -71.483376 | N34: 20.27 | O34: oui | P34: Plane | Q34: 3 | R34: W | S34: 10 | T34: FADQ et mesures Démeter | Y34: 6.5 | AM34: =G34/N34 -> 12950.173
A35: 26058624 | C35: 44166 | D35: Bibianne Daneau | E35: Denis Courchesne | F35: 5 743 071, 5 743 223 | G35: 1043700 | I35: Nicolet-Yamaska | J35: Pierreville | K35: Rg Courchesne, Rg du Petit-Bois Pierreville | L35: 46.107132 | M35: -72.813624 | N35: =25.8+21.49 -> 47.29 | O35: oui | P35: Plane | Q35: 3 et 4 | R35: FW | S35: =9.3+3.9+24.4-0.3 -> 37.3 | T35: Demeter | U35: 25.8 | V35: infosols | Y35: 0.4 | AM35: =G35/N35 -> 22070.205
A36: 25988798 | C36: 44210 | D36: 9377-2416 Quebec Inc. | E36: Teri Chelminski | F36: 3977389 | G36: 607 959 | J36: 0 ch de Senneville | K36: 0 | AJ36: Boisé pour constrution | AM36: =G36/N36 -> #VALUE!
A37: 26028123 | C37: 44211 | D37: FERME DATONY ENR | E37: FERME L. POULIOT & FILS INC., | F37: 3 586 505, 3 586 507 | G37: 615000 | I37: Bellechasse | J37: Honfleur | K37: Rang Buckland | L37: 46.619615 | M37: -70.82386 | N37: 41.6 | O37: Oui | P37: Legere pente | Q37: 7 | R37: P | S37: =15.4+8.7+16.1 -> 40.2 | T37: FADQ | U37: 0 | V37: infosols | X37: Foin, céréales | AM37: =G37/N37 -> 14783.654
A38: 26038743 | C38: 44230 | D38: Anne LEGAULT | E38: 9423-0695 QUÉBEC INC | F38: 4 852 645, 6 302 527, 4 852 680 | G38: 280000 | I38: Papineau | J38: Lochaber | K38: Route 148 Est, Lochaber | L38: 45.600339 | M38: -75.215190 | N38: 42.62 | O38: oui | P38: Legere pente | Q38: 2 | R38: W | S38: 24.7 | T38: FADQ | U38: 24.7 | V38: infosol | Y38: 15.8 | AM38: =G38/N38 -> 6569.6856
A39: 26366489 | C39: 44238 | D39: Cyrille LEFEBVRE | E39: FERME GERVILLE INC (Simon Lefebvre) | F39: 5 433 072, 5 434 197 | G39: 1200000 | I39: Nicolet-Yamaska | J39: Baie-du-Febvre | K39: Route Marie-Victorin Baie-du-Febvre | N39: 60.83 | O39: oui | P39: Plane | Q39: 2 | R39: W | S39: =3.9+3.7+1.5+1.7+2.7+0.8+20.7+10.6 -> 45.6 | T39: FADQ | U39: =2.7+0.8+20.7+10.6 -> 34.8 | V39: infosols | Y39: 11.5 | AL39: 435204 | AM39: =G39/N39 -> 19727.108
A40: 26855053 | C40: 44248 | D40: LORRAIN HEPPELL | E40: Nadine HEPPELL | F40: 5 148 902, 5 148 914, 5 149 044 | G40: 270000 | I40: Manicouagan | J40: Ragueneau | K40: 2ieme rang, Ragueneau | L40: 49.099037 | M40: -68.46945 | N40: 143.99 | O40: oui | P40: legere pente | Q40: 7 | R40: w | S40: 35.4 | T40: FADQ et mesures Démeter | U40: 0 | V40: infosol | Y40: 105.59 | AA40: 3 | AM40: =G40/N40 -> 1875.1302
A41: 26089976 | C41: 44251 | D41: 9116-3493 QUÉBEC INC. Yvan LUSIGNAN | E41: LES ENTREPRISES PHILIPPE DAIGNEAULT INC | F41: 2114957 | G41: 600000 | I41: Longueuil | J41: Saint-Bruno-de-Montarville | K41: Grand Boulevard Ouest, Saint-Bruno-de-Montarville | N41: 10.87 | Q41: 2 | R41: W | S41: 10.3 | AM41: =G41/N41 -> 55197.792
A42: 26092156 | C42: 44252 | D42: Charles MARCIL | E42: 2741-9605 QUÉBEC INC Stéphane LAMOUREUX | F42: 2600991 | G42: 2050000 | J42: Carignan | K42: chemin Salaberry à Carignan | N42: 40.67 | Q42: 2 | R42: W | S42: 39.7 | AM42: =G42/N42 -> 50405.704
A43: 26097728 | C43: 44253 | D43: Developpement Simi Inc. | E43: Lotissement Sm Inc. | F43: 6405922 (Nv lot: 6 432 893, 6 432 894 et 6 432 895) | G43: 125 000 | J43: Notre-Dame-De-L'Ile-Perrot | K43: 0 | AJ43: Lotissement résidentiel | AM43: =G43/N43 -> #VALUE!
A44: 26252826 | C44: 44265 | D44: Francine GOULET | E44: FERME PROLIFIC INC (Donald CY, et Marie-Pier PERREAULT) | F44: 3581441 | G44: 271920 | I44: Nouvelle Beauce | J44: Saint-Elzéar | K44: rang du Bas-Sainte-Anne Saint-Elzéar | L44: 46.414588 | M44: -71.147432 | N44: 20.42 | O44: Oui | P44: Plane | Q44: 3 | R44: PT | S44: 20 | T44: FADQ | X44: Maïs | AM44: =G44/N44 -> 13316.357
A45: 26128298 | C45: 44266 | D45: AMENAGEMENT CAVALCADE INC Cathie SMITH | E45: Martin VINCENT | F45: 2 600 789, 2 601 052 | G45: 750000 | N45: =(132355.5)/10000+0.02 -> 13.25555 | AK45: lot 2 600 789 devenu 6 453 819 et 6 453 818. Bordure chemin de Chambly | AM45: =G45/N45 -> 56580.074
A46: 26243246 | C46: 44266 | D46: Daniel Belval | E46: FERME J.T Chagnon & Fils inc. | F46: 1 956 894 | G46: 1137500 | I46: les Maskoutains | J46: Sainte-Hélène-de-Bagot | K46: 2e rang Sainte-Hélène-de-Bagot | L46: 45.706195 | M46: -72.727843 | N46: 23.42 | O46: oui | P46: Plane | Q46: 3 | R46: FW | S46: 22.1 | T46: FADQ | U46: 22.1 | V46: infosol | Y46: 0 | AL46: 439817 | AM46: =G46/N46 -> 48569.599
A47: 26550934 | C47: 44272 | D47: FERME DUVERGER S.E.N.C. (Marie-Ève GODBOUT et Alain GAGNÉ) | E47: SOCIÉTÉ DA-MY S.E.N.C. (Myriane GARON et David CYR) | F47: 3581512 | G47: 225000 | I47: Nouvelle Beauce | J47: Saint-Elzéar | K47: Saint-Elzéar | L47: 46.407981 | M47: -71.111959 | N47: 13.21 | O47: Oui | P47: Plane | Q47: 4 | R47: PT | S47: 11.6 | T47: FADQ | U47: 11.6 | V47: infosols | Y47: 0.5 | AL47: 045119 | AM47: =G47/N47 -> 17032.551
A48: 26151057 | C48: 44277 | D48: Alain HÉBERT | E48: FERME MONDRÉ INC Marc-André CHAGNON | F48: 4 833 075, 4 833 660 | G48: 1300000 | I48: La-Vallée-du-Richelieu | J48: Saint-Antoine-sur-Richelieu | K48: Rang de l'Acadie, Saint-Antoine-sur-Richelieu | L48: 45.795692 | M48: -73.197964 | N48: 28.52 | O48: Oui | P48: plane | Q48: 2 | R48: W | S48: 27 | U48: =Table3[[#This Row],[Superficie cultivée (ha)]] -> 27 | AL48: 310880 (Aliénation / lotissement,Morcellement de ferme Utilisation non agricole seule,Agrand. usage exist. ou access,Résid. non rattach. à une terr) | AM48: =G48/N48 -> 45582.048
A49: 27666634 | C49: 44286 | D49: 2319-0887 Quebec Inc. (Denise Séguin) | E49: Municipalite Des Cedres (Bernard Daoust) | F49: 6536420, 6536419 | G49: 1250000 | I49: Vaudreuil-Soulanges | J49: Les Cedres | K49: 0 | N49: 3.94 | O49: non | S49: 3.94 | AJ49: Terrain redéveloppé Petite terre, prox. Devl | AK49: 0 | AL49: Décision430302 | AM49: =G49/N49 -> 317258.88
A50: 26210604 | C50: 44300 | D50: FERME PATENAUDE ENR Jean-Denis PATENAUDE | E50: LES MARAÎCHERS BEC SUCRÉ INC Denis DESGROSEILLIERS | F50: 2867218 | G50: 600000 | I50: Roussillon | J50: St-Isidore | K50: Rang St-Régis, St-Isidore | L50: 45.307764 | M50: -73.675017 | N50: 9.92 | O50: Oui | P50: plane | Q50: 2 | R50: W | S50: 9.3 | U50: =Table3[[#This Row],[Superficie cultivée (ha)]] -> 9.3 | AM50: =G50/N50 -> 60483.871
A51: 26211099 | C51: 44300 | D51: Jean-Hubert DUBOIS | E51: AGRICOLE S.A.E.L.B. INC Martin FORTIER | F51: 1 912 195, 1 912 198, 1 912 680, 1 912 938, 2 436 410 | G51: 1900000 | I51: Longueuil | J51: Boucherville | K51: 1291, chemin du Général-Vanier, Boucherville | N51: =8.71+5.04+20.05+27886.3/10000+7.99+0.5 -> 45.07863 | Q51: 2 | R51: W | S51: =7.9+2.8+1.3+0.7+3.6+12 -> 28.3 | AC51: 1 maison | AK51: Bordure route 132. Lots non contigus. Lot 1912195 devenu 6586481 et 6586480. 2 436 410 partie du lot 6558038 | AM51: =G51/N51 -> 42148.575
A52: 26221568 | C52: 44302 | D52: 9116-3493 QUÉBEC INC. Yvan LUSIGNAN | E52: LES ENTREPRISES PHILIPPE DAIGNEAULT INC | F52: 2 114 752, 2 112 016 | G52: 3000000 | I52: Longueuil | J52: Saint-Bruno-de-Montarville | K52: Grand Boulevard Ouest, Saint-Bruno-de-Montarville | N52: =26.25+37.65 -> 63.9 | Q52: 2 | R52: W | S52: 53 | Y52: 7.2 | AF52: Hangar état moyen 6000 pc | AM52: =G52/N52 -> 46948.357
A53: 26229695 | C53: 44307 | D53: PIERRE DU MOULIN INC (Rudy Laixhay) | E53: FERME DU GOUFFRE S.E.N.C. (Nicol Simard et Lucie Tremblay) | F53: 4001203, 4001215 | G53: 135000 | I53: Charlevoix | J53: Baie-Saint-Paul | K53: Chemin Saint-Laurent Baie-Saint-Paul | L53: 47.509150 | M53: -70.494905 | N53: =(323671.7-392.15)/10000 -> 32.327955 | O53: oui | P53: Plane | Q53: 3 | R53: F | S53: =0.8+3.6+1.4+0.3 -> 6.1 | T53: Mesures Demeter | Y53: =Terre!$N31-Terre!$S31-Terre!#REF! -> #REF! | AM53: =G53/N53 -> 4175.9524
A54: 26235746 | C54: 44308 | D54: Ferme M. Lavoie inc (Réjean Côté) | E54: Groupe Lamoureux 2021 inc (Stéphane Lamoureux) | F54: 2600802, 2600999, 2601004, 2601021 | G54: 12483700 | I54: La-Vallée-du-Richelieu | J54: Carignan | K54: Chemin Salaberry, Carignan | L54: 45.428160 | M54: -73.321445 | N54: =4.17+50.27+139.51+0.37 -> 194.32 | O54: Oui | P54: plane | Q54: 2 | R54: W | S54: à calculer | U54: à calculer | Y54: 5.6 | AK54: 1 lot article 59 | AM54: =G54/N54 -> 64243.001
A55: 26261637 | C55: 44316 | D55: FERME BEAU SITE 2015 INC. | E55: FERME S. PARÉ ET FILS S.E.N.C. | F55: 3587452 | G55: 400000 | I55: Bellechasse | J55: Honfleur | L55: 46.653735 | M55: -70.867996 | N55: 16.39 | O55: Oui | P55: Legere pente | Q55: 3 | R55: FT | S55: 16.1 | T55: FADQ | U55: non | V55: infosols | X55: Foin, soya | AL55: 443044 | AM55: =G55/N55 -> 24405.125
A56: 26264149 | C56: 44319 | D56: FERME FRANÇOIS CHAMPAGNE ENR. | E56: FERME RICHARD QUINTAL & FILS SENC. | F56: 2925751 | G56: 1095000 | I56: Acton | J56: Acton Vale | K56: Rang 2, Acton Vale | L56: 45.612907 | M56: -72.632196 | N56: 26.03 | O56: oui | P56: Plane | Q56: 4 | R56: FW | S56: 23.5 | T56: FADQ | U56: 0 | Y56: 0 | AM56: =G56/N56 -> 42066.846
A57: 26317047 | C57: 44335 | D57: Ferme Maurite Guertin (Réjean Côté) | E57: 9441-8068 Québec inc (Steve Mathieu) | F57: 2951305, 2 044645 , 3138455 | G57: 540000 | I57: La-Vallée-du-Richelieu | J57: Carignan | K57: Carignan | N57: =(123752.7)/10000+0.04 -> 12.41527 | Q57: 2 | R57: W | S57: 11 | AK57: Bordure de l'A10 | AL57: 316919 (Nouvel usage,Énergie) | AM57: =G57/N57 -> 43494.825
A58: 26318138 | C58: 44335 | D58: FERMES CHRISTIAN ET JOSÉE S.E.N.C., | E58: Guillaume LACHAINE | F58: 5 090 178, | G58: 130000 | I58: antoine-labelle | J58: Ferme-neuve | N58: 35.29 | O58: oui | AM58: =G58/N58 -> 3683.7631
A59: 26317141 | C59: 44335 | D59: Les cultures CRC inc (Réjean Côté), Ferme agricole Côté inc (Réal Côté) | E59: Ferme BJD SENC (Bernard Gélineau) | F59: 2600981, 2601663, 2601681 | G59: 4800000 | I59: La-Vallée-du-Richelieu | J59: Carignan | L59: 45.407568 | M59: -73.334088 | N59: =5.12+21.87+27.57 -> 54.56 | O59: Oui | P59: plane | Q59: 2 | R59: W | S59: =28.7+5.2+4.9+5.1+3.9 -> 47.8 | U59: 24.1 | Y59: 3.5 | AK59: 3 lots séparés | AL59: 316919 (énergie) | AM59: =G59/N59 -> 87976.54
A60: 26326467 | C60: 44337 | D60: SUCCESSION GISELE GEMME | E60: LES GAZONNIÈRES FAIRLAWN JUNIOR INC Gabriel RICHER | F60: 5881446 | G60: 1000000 | I60: Marguerite-D'Youville | J60: Sainte-Julie | N60: 24.73 | Q60: 4 | R60: W | S60: 18.6 | AK60: Servitude de passage (fonds dominant). Lignes Hydro-Québec sur toute la longueur. Bordure A10 | AL60: 349764 (Nouvel usage,Énergie) | AM60: =G60/N60 -> 40436.717
A61: 26326353 | C61: 44337 | D61: Steve BLANCHETTE | E61: FERME ST-CHARLES INC Stéphane BLANCHETTE | F61: 3408316 | G61: 1100000 | I61: La-Vallée-du-Richelieu | J61: Saint-Charles-sur-Richelieu | K61: 4e rang Sud, Saint-Charles-sur-Richelieu | L61: 45.645598 | M61: -73.131880 | N61: 32.86 | O61: Oui | P61: plane | Q61: 3 | R61: F | S61: 22.7 | Y61: 8.9 | AK61: servitude de passage en faveur d’Ultramar | AM61: =G61/N61 -> 33475.35
A62: 26326699 | C62: 44337 | D62: FERME ST-MARIN ET FRERES SENC. | E62: FERME VITELLO INC. | F62: 6433796 | G62: 3900000 | I62: Montérégie | J62: Saint-Nazaire-d'Acton | K62: Rang 12e, Saint-Nazaire-d'Acton | L62: 45.763130 | M62: -72.611947 | N62: 94.1 | O62: oui | P62: legere pente | Q62: 3 | R62: FW | S62: 93.5 | T62: FADQ | U62: 93.5 | V62: infosol | Y62: 0 | AK62: Forme optimale, Partie en classe 2 | AM62: =G62/N62 -> 41445.271
A63: 26353810 | C63: 44347 | D63: 7512830 CANADA INC (Danyel PHÉNIX) | E63: 6342485 CANADA INC (Vincenzo BARRASSO) | F63: 2601047 | G63: 4150000 | I63: La-Vallée-du-Richelieu | J63: Carignan | K63: chemin Bellerive Carignan | L63: 45.445506 | M63: -73.323945 | N63: 50.99 | O63: oui | P63: plane | Q63: 2 | R63: W | S63: =40.9+4.4+0.3 -> 45.6 | T63: FADQ | Y63: 1.8 | AM63: =G63/N63 -> 81388.508
A64: 26353810 | C64: 44347 | D64: 7512830 Canada Inc. (Danyel PHÉNIX) | E64: 6342485 Canada Inc. (Vincenzo BARRASSO) | F64: 2601047 | G64: 4150000 | J64: Carignan | K64: 0 ch Bellerive | N64: 50.99 | S64: 45.6 | Y64: 2,5 | AG64: Aucune | AH64: 0 | AM64: =Table3[[#This Row],[Prixdevente($)]]/Table3[[#This Row],[Superficie cultivée (ha)]] -> 91008.772
A65: 26357278 | C65: 44348 | D65: Caroline TAILLEUR | E65: FERME TROISCÔTES INC | F65: 6 364 423, 6 186 694 | G65: 458000 | I65: L'Ile-d'Orléans | J65: Saint-pierre-de-l'ile-d'orléans | L65: 46.923245 | M65: -71.027517 | N65: 70.01 | O65: oui | P65: Légère pente | Q65: 3 et 7 | R65: FT | S65: 40.4 | T65: FADQ | Y65: 28.61 | AK65: bâtiment sur la terre | AM65: =G65/N65 -> 6541.9226
A66: 26380899 | C66: 44355 | D66: GESTION DANY LAGACÉ INC | E66: GESTION ALOA INC Larry ST-ONGE | F66: 5035394 | G66: 276849 | I66: Lévis | J66: route Marie-Victorin, Lévis | L66: 46.700212 | M66: -71.447347 | N66: 2.98 | O66: oui | P66: plane | Q66: 3 | R66: I | S66: 2 | T66: Mesures Demeter | Y66: 0.7 | AK66: Bord du fleuve | AM66: =G66/N66 -> 92902.349
A67: 26386123 | C67: 44355 | D67: Susan Irene Marshall | E67: Douglas Stewart Mossey | F67: 2070487 | G67: 5 500 | J67: Notre-Dame-De-L'Ile-Perrot | K67: 0 boul St-Joseph | AM67: =G67/N67 -> #VALUE!
A68: 26419296 | C68: 44364 | F68: 6436864 | G68: 100000 | I68: Témiscouata | J68: Saint-eusèbe | K68: Route prinicpale, Saint-Eusèbe | L68: 47.540934 | M68: -68.912017 | N68: 24.81 | O68: En partie | P68: pente | Q68: 4 | R68: T | S68: 19.7 | T68: FADQ | Y68: 5.11 | AM68: =G68/N68 -> 4030.6328
A69: 27564495 | C69: 44373 | D69: Jean-Luc GOSSELIN | E69: FERME FX ORLÉANS INC (Philippe BEAULIEU) | F69: 6 282 076, 6 282 233 | G69: 725000 | I69: L'Ile-d'Orléans | J69: Saint-François-de-l'île-d'Orléans | K69: chemin Royal Saint-François-de-l'île-d'Orléans | L69: 46.978109 | M69: -70.848473 | N69: =41.16+8.46 -> 49.62 | O69: oui | P69: Légère pente | Q69: 3 | R69: F | S69: =1.9+5.9+0.8+3.2+1.6+1.5+2.7+1.9 -> 19.5 | T69: FADQ | Y69: 25.6 | AM69: =G69/N69 -> 14611.044
A70: 26457351 | C70: 44375 | D70: Ferme Bernard GARIEPY | E70: Mickael THIBAULT | F70: 3233527 | G70: 10000 | I70: Portneuf | J70: Deschambault-Grondines | K70: 2e rang Deschambault-Grondines | L70: 46.639754 | M70: -72.008068 | N70: 0.43 | O70: Oui | P70: Plane | Q70: 4 | R70: FW | S70: 0.43 | T70: FADQ | U70: 0 | V70: Infosols | X70: - | AK70: Pas d'accès direct, grange | AM70: =G70/N70 -> 23255.814
A71: 27970139 | C71: 44376 | D71: Marielle CÔTÉ | E71: Patrick RACINE | F71: 6 265 965 | G71: 200000 | I71: Brome-Missisquoi | J71: Dunham | K71: rue Principale, Dunham | L71: -72.798091 | M71: 45.150205 | N71: 10.37 | O71: oui | P71: Plane | Q71: 3 | R71: F | S71: =5.1+2+0.6 -> 7.7 | T71: FADQ et mesures Déméter | U71: 0 | V71: Infosol | Y71: =0.8 -> 0.8 | AK71: non Drainée, partie en classe 7 | AM71: =G71/N71 -> 19286.403
A72: 26468272 | C72: 44379 | D72: 9213-5466 QUÉBEC INC Dominique Cimon | E72: FERME SIMAJÉ INC Christian Riendeau | F72: 5821091 | G72: 650000 | I72: Roussillon | J72: Mercier | K72: Rang Saint-Charles, Mercier | L72: 45.308774 | M72: -73.768482 | N72: 19.119 | O72: Oui | P72: plane | Q72: 2 | R72: W | S72: =13.7+3.5 -> 17.2 | U72: =Table3[[#This Row],[Superficie totale (ha)]] -> 19.119 | AM72: =G72/N72 -> 33997.594
A73: 26508558 | C73: 44391 | D73: Ferme C.M. Gagnon Inc. | E73: Ferme Lugano Inc. | F73: 3259720, 3259693 | G73: 650000 | I73: Bellechasse | J73: Saint-Charles-de-Bellechasse | K73: 2ième Rang Ouest | L73: 46.839722 | M73: -70.898266 | N73: 40.4 | O73: Oui | P73: Legere pente | Q73: 3 | R73: F | S73: 34.8 | T73: FADQ | U73: non | V73: Infosols | X73: Soya, foin | Y73: 4.7 | AK73: non drainée | AM73: =G73/N73 -> 16089.109
A74: 26584619 | C74: 44424 | D74: FERME VERGON INC. | E74: FERME J.E.S. POULIOT INC. | F74: 6 449 114, 6 449 113 | G74: 500000 | I74: Bellechasse | J74: Saint-Charles-de-Bellechasse | K74: 2e Rang Est | L74: 46.721951 | M74: -70.808118 | N74: 23.32 | O74: Oui | P74: Legere pente | Q74: 5 | R74: TP | S74: 15.3 | T74: FADQ et mesures Démeter | U74: non | V74: Infosols | X74: Soya, foin | Y74: 8.02 | AK74: non drainée | AM74: =G74/N74 -> 21440.823
A75: 26670227 | C75: 44456 | D75: R. Howard Webster Foundation | E75: Ville De Montreal | F75: 4590357 | G75: 700000 | J75: Île Bizard | K75: 0 rue Cherrier | N75: 5.71 | O75: non | AJ75: Boisé | AK75: 0 | AM75: =G75/N75 -> 122591.94
A76: 26670225 | C76: 44456 | D76: R. Howard Webster Foundation | E76: Ville De Montreal | F76: 4590336 | G76: 750000 | J76: Île Bizard | K76: 0 rue Cherrier | N76: 8.84 | O76: non | AJ76: Boisé | AK76: 0 | AM76: =G76/N76 -> 84841.629
A77: 26668396 | C77: 44456 | D77: Richard FERLAND | E77: LE VIGNOBLE DE L'ISLE DE BACCHUS INC | F77: 6 186 584, 6 186 588 | G77: 600000 | I77: L'Ile-d'Orléans | J77: Saint-pierre-de-l'ile-d'orléans | N77: 24.83 | O77: oui | P77: pente importante | Q77: 4 et 3 | R77: FT | S77: 9.1 | T77: FADQ | Y77: 15.73 | AK77: Verger semble sur la terre | AM77: =G77/N77 -> 24164.317
A78: 27009141 | C78: 44462 | D78: Jean-François PELLETIER | E78: FERME POCATOISE LTÉE (Charles-Étienne PELLETIER) | F78: 6487110 | G78: 250000 | I78: Kamouraska | J78: Sainte- Anne-de-la-Pocatière | K78: chemin de la Montagne-Thiboutot Sainte- Anne-de-la-Pocatière | L78: 47.362847 | M78: -69.967281 | N78: 30.41 | O78: oui | P78: Plane | Q78: 3 | R78: WD | S78: 28.51 | T78: Mesures Demeter | Y78: 1.9 | AK78: non drainée | AM78: =G78/N78 -> 8220.9799
A79: 26703053 | C79: 44469 | D79: Simonne ROUILLIER | E79: FERMES DEUX-MONT INC Sylvain BENOIT | F79: 4149088 | G79: 1050000 | I79: La-Vallée-du-Richelieu | J79: St-Jean-Baptiste | K79: Rang de la rivière Sud ,St-Jean-Baptiste | L79: 45.508635 | M79: -73.135505 | N79: 26.61 | O79: Oui | P79: plane | Q79: 2 | R79: W | S79: 25.8 | U79: =Table3[[#This Row],[Superficie cultivée (ha)]] -> 25.8 | AM79: =G79/N79 -> 39458.85
A80: 27375663 | C80: 44469 | D80: Renald Latraverse | E80: Fruits Des Iles Inc.(r Éric LUPIEN) | F80: 6402084 | G80: 80000 | I80: Pierre-De-Saurel | J80: Ste-Anne-De-Sorel | K80: Chemin du Chenal du Moine | N80: 5,21 ha | O80: Oui | Q80: 2-W | S80: 35.1 | U80: 0 | Y80: 0 | AG80: 0 | AH80: 0 | AL80: 434981; Autorisation; Aliénation/Lotissement,Morcellement de terres | AM80: =Table3[[#This Row],[Prixdevente($)]]/Table3[[#This Row],[Superficie cultivée (ha)]] -> 2279.2023
A81: 26711833 | C81: 44473 | F81: 4765940 | G81: 21500 | I81: Témiscouata | J81: Saint-eusèbe | K81: Route prinicpale, Saint-Eusèbe | L81: 47.539847 | M81: -68.907983 | N81: 9.71 | O81: En partie | P81: pente | Q81: 4 | R81: T | S81: 6.5 | T81: FADQ et mesures | Y81: 3 | AM81: =G81/N81 -> 2214.2122 | AO81: =(AM155-Table3[[#This Row],[Taux unitaire global ($/ha)]])/Table3[[#This Row],[Taux unitaire global ($/ha)]] -> 20.756374
A82: 26743901 | C82: 44487 | D82: Pierre BACHAND, Lyne MONTPETIT | E82: 9445-4279 QUÉBEC INC Sylvain BERGERON | F82: 2 267 359, 6 270 108, 6 330 896 | G82: 1550000 | I82: Roussillon | J82: Laprairie | K82: Rang St-Raphael, Laprairie | L82: 45.380522 | M82: -73.431160 | N82: =16.27+12.95+13.96 -> 43.18 | O82: Oui | P82: plane | Q82: 2 | R82: W | S82: =18+5.4+9 -> 32.4 | Y82: 8 | AK82: Droit de refus au profit de l'acheteur du lot 6 330 897 | AM82: =G82/N82 -> 35896.248
A83: 26751495 | C83: 44489 | D83: Andre DEXTRAZE | E83: FERME DESTRAMBLEY | F83: 1 840 247, 1 840 986, 6 439 711, 6 439 719 | G83: 1935738 | I83: les Maskoutains | J83: Saint Simon | K83: Rang Saint-Édouard | L83: 45.701842 | M83: -72.808342 | N83: 52.52 | O83: oui | P83: Plane | Q83: 3 | R83: FW | S83: 51 | T83: Mesures Démeter | U83: 51 | V83: infosol | Y83: 0 | AK83: majoritairement boisée, non drainé | AM83: =G83/N83 -> 36857.159
A84: 27026715 | C84: 44490 | D84: FERME G C K MARTEL S.E.N.C (M. Georges Martel) | E84: SIDCLOVI INC (SIDCLOVI INC) | F84: 5743134 | G84: 1500000 | I84: Nicolet-Yamaska | J84: Pierreville | K84: rang du Petit-Bois Pierreville | L84: 46.104932 | M84: -72.787986 | N84: 55.53 | O84: oui | P84: Plane | Q84: 4 | R84: FW | S84: 43.1 | T84: FADQ | U84: =Terre!$S45 -> 0 | V84: infosols | Y84: 10.7 | AK84: non drainée | AM84: =G84/N84 -> 27012.426
A85: 26782656 | C85: 44501 | D85: Ghislaine GIRARD | E85: FERME YANNIC LÉTOURNEAU INC | F85: 3 800 831, 3 800 837 | G85: 460000 | I85: Roussillon | J85: Saint-Constant | L85: 45.361130610079925 | M85: -73.57754457324118 | N85: =9.46+1.81 -> 11.27 | O85: Oui | P85: plane | Q85: 2 | R85: W | S85: 10.6 | U85: 9 | AK85: servitude de non-accès à l'autoroute 30 | AM85: =G85/N85 -> 40816.327
A86: 26792696 | C86: 44504 | D86: Marcel FORTIN, Paul FORTIN | E86: FERME DESBOISÉS INC | F86: 3259618 | G86: 100000 | I86: Bellechasse | J86: Saint-Michel-de-Bellechasse | K86: 3e rang Est Saint-Michel-de-Bellechasse | L86: 46.854064 | M86: -70.872593 | N86: 5.83 | O86: Oui | P86: Plane | Q86: 3 | R86: W | S86: =3.3+1.5 -> 4.8 | T86: FADQ | U86: 0 | V86: Infosols | Y86: 0.6 | AK86: îlot destructuré | AM86: =G86/N86 -> 17152.659
A87: 27604910 | C87: 44504 | D87: Vincent BLOUIN | E87: GESTION BEAU LIEU INC (Philippe BEAULIEU) | F87: 6 282 003, 6 282 024 | G87: 675000 | I87: L'Ile-d'Orléans | J87: Saint-Jean-de-l'Ile-d'Orléans | K87: 4392, chemin Royal Saint-Jean-de-l'Ile-d'Orléans | L87: 46.952156 | M87: -70.906884 | N87: =31.66+0.83 -> 32.49 | O87: oui | P87: Plane | Q87: 3 | R87: F | S87: =0.6+6.5+6.4+4.6+4.4 -> 22.5 | T87: FADQ | U87: =Terre!$S63 -> 45.6 | V87: infosols | Y87: =0.2+9.7 -> 9.9 | AK87: Presence d'un batiment, non drainée | AM87: =G87/N87 -> 20775.623
A88: 26821704 | C88: 44516 | D88: Normand NOISEUX | E88: FERME NORMI S.E.N.C Normand NOISEUX et Mireille BIENVENUE | F88: 4 149 084, 4 149 300 | G88: 1275789 | I88: La-Vallée-du-Richelieu | J88: Saint-Jean-Baptiste | K88: Rang de la Rivière Nord, Saint-Jean-Baptiste | L88: 45.497831 | M88: -73.165272 | N88: =27.93+2.66 -> 30.59 | O88: Oui | P88: plane | Q88: 2 et 4 | R88: W | S88: 22 | U88: =Table3[[#This Row],[Superficie cultivée (ha)]]-2.2 -> 19.8 | Y88: 6.7 | AK88: Avec équipemens agricoles et semences | AM88: =G88/N88 -> 41706.08
A89: 26832418 | C89: 44519 | D89: Ecodev Inc. | E89: J.S. Procom Inc. | F89: 6429811 | G89: 35 000 000 | J89: Notre-Dame-De-L'Ile-Perrot | K89: 0 av Forest | AM89: =G89/N89 -> #VALUE!
A90: 26832418 | C90: 44519 | D90: Ecodev Inc. | E90: J.S. Procom Inc. | F90: 6429810 | G90: 35 000 000 | J90: Notre-Dame-De-L'Ile-Perrot | K90: 0 av Forest | AM90: =G90/N90 -> #VALUE!
A91: 26836786 | C91: 44523 | D91: Marcel BOILEAU | E91: Sinan TEZGEL | F91: 4589867 | G91: 580000 | J91: Île Bizard | K91: rue Cherrier | N91: 14.74 | O91: 433201; Autorisation; Article 15.2 | Q91: 2X, 4FM, 2W | S91: 5.4 | U91: 0 | V91: Bon 30%, imparfait 30% et mauvais 30% | Y91: 9.34 | AJ91: Terre | AK91: 0 | AM91: =G91/N91 -> 39348.711
A92: 27028838 | C92: 44532 | D92: Edmond Martin | E92: Ferme N.C. Amesse S.E.N.C. (Normand Amesse) | F92: 4516571 | G92: 140 000 | J92: Salaberry-De-Valleyfield | K92: 0 | AJ92: Terre proximité devlop. | AM92: =G92/N92 -> #VALUE!
A93: 26868217 | C93: 44533 | D93: Gilles , René BILODEAU | E93: FERME BERTHIER-SUR-MER INC | F93: 3475163 | G93: 150000 | I93: Montmagny | J93: Berthier-sur-Mer | K93: Boulevard Blais Ouest Berthier-sur-Mer | L93: 46.914629 | M93: -70.73863 | N93: 12.87 | O93: Oui | P93: relativement plane | Q93: 3 | R93: F | S93: =1.7+3.7+2.7+1.8 -> 9.9 | T93: FADQ | U93: 0 | V93: Infosols | AM93: =G93/N93 -> 11655.012
A94: 27096308 | C94: 44540 | D94: François BÉLANGER | E94: 9085-9513 QUÉBEC INC (Étienne ROY) | F94: 3590851 | G94: 1000000 | I94: Lotbinière | J94: Sainte-Croix | K94: rang du Petit-Village Baie-du-Febvre | L94: 46.617319 | M94: -71.760982 | N94: 40.93 | O94: oui | P94: Plane | Q94: 2 | R94: F | S94: =6.1+5.5+5+7+5.7+3.8+7 -> 40.1 | T94: FADQ | AK94: Terres louées, Présence d'un hangar, boisé en forte pente (feuillus), environ 20 ha en friches et 10 ha de terres non cultivables en l'état | AM94: =G94/N94 -> 24431.957
A95: 26889712 | C95: 44545 | D95: Gabrielle BLANC BOUVIER | E95: 9341-6691 QUEBEC INC India BIENVENUE | F95: 3078518 | G95: 1500000 | I95: La-Vallée-du-Richelieu | J95: Saint-Basile-le-Grand | K95: 5, rue Principale, Saint-Basile-le-Grand | N95: 16.06 | S95: =6.8+7 -> 13.8 | AC95: 1 maison | AM95: =G95/N95 -> 93399.751
A96: 26940266 | C96: 44546 | D96: Clément PAQUET | E96: FERME RAYMOND DORÉ & FILS INC. | F96: 3 826 259 | G96: 200000 | I96: Portneuf | J96: Pont-Rouge | K96: la route Grand-Capsa, Pont-Rouge | L96: 46.758035 | M96: -71.652391 | N96: 9.55 | O96: oui | P96: Plane | Q96: 3 | R96: F | S96: 8.4 | T96: FADQ | U96: 0 | V96: infosol | X96: avoine | Y96: 1 | AK96: Présence de 3 hangars (état moyen) | AM96: =G96/N96 -> 20942.408
A97: 26908213 | C97: 44547 | D97: SOCIÉTÉ EN COMMANDITE FERMES AUX PORTES DE LA NATURE | E97: 9454-3162 QUÉBEC INC Pierrick GRIPON | F97: 6018035 | G97: 1228500 | I97: Roussillon | J97: Mercier | K97: Bd Ste-Marguerite, Mercier | L97: 45.292106 | M97: -73.726854 | N97: 33.15 | O97: Oui | P97: plane | Q97: 2 | R97: W | S97: =18.6+11.9-1+2.5 -> 32 | U97: =Table3[[#This Row],[Superficie totale (ha)]] -> 33.15 | AL97: 3 autorisations caduques (Utilisation non agricole seule,Nouvel usage,Subst. min. granul. (sab-grav)0 | AM97: =G97/N97 -> 37058.824
A98: 27103157 | C98: 44552 | D98: LOUISETTE PARADIS | E98: FERME J.P. CÔTÉ & FILS INC (Janie Côté) | F98: 5 004 434, 5 004 436, 3 055 746 | G98: 400000 | I98: Québec | J98: Saint-Augustin-de-Desmaures | K98: ch du Petit Village Nord Saint-Augustin-de-Desmaures | L98: 46.737014 | M98: -71.529517 | N98: =12.77+5.6+1.17 -> 19.54 | O98: oui | P98: Plane | Q98: 3 et 4 | R98: W | S98: =8.5+5.4+3.9 -> 17.8 | T98: FADQ | U98: 0 | Y98: 0.3 | AK98: drainée, terre cultivable disperser | AM98: =G98/N98 -> 20470.829
A99: 26929475 | C99: 44566 | D99: FERME DAUPHINAIS ET BLAIN S.E.N.C | E99: GESTION NICOLAS PERREAULT INC | F99: 3407933 | G99: 1500000 | I99: La Vallée-du-Richelieu | J99: Saint-Denis-sur-Richelieu | K99: 3e rang des Moulins ouest, Saint-Denis-sur-Richelieu | L99: 45.748728 | M99: -73.138876 | N99: 36.12 | O99: oui | P99: Déclivité modérée | Q99: 2 | R99: WT | S99: =2.7+16.9+14.1 -> 33.7 | T99: FADQ | U99: 33.7 | V99: infosol | Y99: 0 | AK99: enclavé | AM99: =G99/N99 -> 41528.239
A100: 26934829 | C100: 44567 | D100: ROSE-HÉLÈNE DEBLOIS | E100: GESTION FAMILLE POMERLEAU INC | F100: 6 473 322, 6 318 636 | G100: 170000 | I100: Lotbinière | J100: Saint-Apollinaire | K100: rang Marigot Saint-Apollinaire | L100: 46.602325 | M100: -71.553605 | N100: 25.31 | O100: Oui | P100: Plane | Q100: 4 | R100: F | S100: 6.5 | T100: FADQ | U100: 0 | V100: Infosols | Y100: =N100-S100 -> 18.81 | AK100: Traverser par une rivière, partiellement | AM100: =G100/N100 -> 6716.7128
...

Sheet Feuil1
A1: Région administrative | B1: Mauricie
A3: MRC | B3: Ville/Municipalité
A4: Les Chenaux | B4: Batiscan
B5: Sainte-Anne de la Pérade
B6: Sainte-Geneviève de Batiscan
B7: Saint-Prosper-de-Champlain
A8: Total Les Chenaux
A9: Total général

Sheet Registre des recherches
A1: Nom de l'analyste | B1: Type de recherche | C1: Date début | D1: Date fin | E1: MRC | F1: Municipalité | G1: Mot clé ferme uniquement | J1: Type de recherche | K1: MRC
A2: Simon | B2: Terres | C2: 45413 | D2: 45580 | E2: Portneuf | G2: oui | J2: Terres et bois | L2: Ferme
A3: Kaka | B3: Terres et bois | C3: 44197 | D3: 45581 | E3: La Côte-de-Beaupré | G3: oui | J3: Terres | K3: Abitibi | L3: Érablière | M3: oui
A4: Kaka | B4: Terres et bois | C4: 45292 | D4: 45593 | E4: Lotbinière | J4: Bois | K4: Abitibi-Ouest | L4: FPE | M4: non
A5: Kaka | B5: Terres et bois | C5: 44927 | D5: 45291 | E5: Lotbinière | F5: Saint-Gilles | J5: Terres -5ha | K5: Acton
A6: Simon | B6: Terres | C6: 44927 | D6: 45600 | F6: Sainte-Martine | G6: oui | J6: Bois -5ha | K6: Antoine-Labelle
A7: Eloi | B7: Terres et bois | C7: 44197 | D7: 45601 | E7: Manicouagan | F7: Ragueneau | J7: Autre (préciser) | K7: Argenteuil
A8: Eloi | B8: Terres et bois | C8: 43466 | D8: 44561 | E8: Manicouagan | J8: Acéricole | K8: Arthabaska
A9: Eloi | B9: Terres et bois | C9: 44927 | D9: 45609 | F9: Saint-Lambert-de-Lauzon | K9: Avignon
A10: Eloi | B10: Terres et bois | C10: 45292 | D10: 45610 | E10: La Nouvelle-Beauce | K10: Beauce-Centre
A11: Eloi | B11: Bois | C11: 44197 | D11: 45621 | F11: Lac frontière | K11: Beauce-Sartigan
A12: Eloi | B12: Bois | C12: 44927 | D12: 45621 | F12: Sainte-Lucie-de-Beauregard | K12: Beauharnois-Salaberry
A13: Eloi | B13: Terres et bois | C13: 44562 | D13: 45623 | E13: Lotbinière | F13: Saint-Agapit | K13: Bécancour
A14: Eloi | B14: Terres et bois | C14: 44562 | D14: 45623 | E14: Lotbinière | F14: Saint-Gilles | K14: Bellechasse
A15: Eloi | B15: Terres et bois | C15: 45292 | D15: 45631 | E15: La Mitis | K15: Bonaventure
A16: Eloi | B16: Terres et bois | C16: 44927 | D16: 45637 | E16: L'Érable | F16: Lyster | K16: Brome-Missisquoi
A17: Eloi | B17: Terres et bois | C17: 44927 | D17: 45637 | F17: Saint-Sylvestre | K17: Charlevoix
A18: Eloi | B18: Terres et bois | C18: 44927 | D18: 45649 | F18: Berthier-sur-mer | K18: Charlevoix-Est
A19: Eloi | B19: Terres et bois | C19: 44927 | D19: 45649 | F19: Saint-francois-de-la-rivère-du-sud | K19: Coaticook
A20: Eloi | B20: Terres | C20: 44927 | D20: 45292 | E20: La Mitis | K20: D'Autray
A21: Eloi | B21: Terres | C21: 45292 | D21: 45680 | E21: Acton | K21: Deux-Montagnes
A22: kaka | B22: Terres | C22: 44562 | D22: 45663 | E22: Beauce-Sartigan | G22: oui | K22: Drummond
E23: Les Etchemins | G23: oui | K23: Joliette
E24: Robert-Cliche | G24: oui | K24: Kamouraska
A25: kaka | B25: Terres et bois | C25: 45474 | D25: 45700 | E25: Kamouraska | G25: oui | K25: La Côte-de-Beaupré
A26: Eloi | B26: Bois | C26: 45566 | D26: 45727 | E26: Portneuf | K26: La Côte-de-Gaspé
A27: Simon | B27: Terres | C27: 45597 | D27: 45765 | F27: Lévis | K27: Lac-Saint-Jean-Est
A28: Simon | B28: Terres | C28: 45597 | D28: 45765 | F28: Beaumont | K28: La Haute-Côte-Nord
A29: Simon | B29: Terres | C29: 45597 | D29: 45765 | F29: St-Charles-de-Bellechasse | K29: La Haute-Gaspésie
A30: Simon | B30: Terres | C30: 45597 | D30: 45765 | F30: St-Henri | K30: La Haute-Yamaska
A31: Simon | B31: Terres | C31: 45663 | D31: 45769 | E31: Beauce-Sartigan | K31: La Jacques-Cartier
A32: Simon | B32: Acéricole | C32: 45663 | D32: 45769 | E32: Beauce-Sartigan | K32: La Matanie (ou Matane [DR])
A33: Simon | B33: Terres | C33: 45108 | D33: 45773 | E33: Québec | K33: La Matapédia
A34: Simon | B34: Bois | C34: 45108 | D34: 45773 | E34: Québec | K34: La Mitis
A35: Simon | B35: Terres | C35: 45703 | D35: 45773 | E35: Portneuf | K35: La Nouvelle-Beauce
A36: ELoi | B36: Bois | C36: 45292 | D36: 45620 | E36: L'Islet | K36: La Rivière-du-Nord
A37: Eloi | B37: Terres et bois | C37: 45444 | D37: 45782 | E37: Vaudreuil-Soulanges | K37: L'Assomption
A38: Eloi | B38: Terres et bois | C38: 45444 | D38: 45782 | E38: Deux-Montagnes | K38: La Vallée-de-la-Gatineau
A39: ELOI | B39: Terres et bois | C39: 45292 | D39: 45784 | E39: Lotbinière | F39: Sainte-croix,Saint-antoine-de-tilly,Saint-appolinnaire,Notre-dame-du-sacré-cœur,lotbinière,saintédouard-de-lotbinière | K39: La Vallée-de-l'Or
A40: Eloi | B40: Terres et bois | C40: 45610 | D40: 45792 | E40: Lotbinière | F40: Saint-gilles | K40: La Vallée-du-Richelieu
A41: Eloi | B41: Bois | C41: 45292 | D41: 45798 | E41: Le Haut-Saint-Laurent | F41: Franklin, Elgin,Hinchinbrooke,Havelock,Saint-chrysostome,ormstown | K41: Le Domaine-du-Roy
A42: Eloi | B42: Bois | C42: 45292 | D42: 45799 | E42: Mékinac | F42: Saint-tite, saint-adelphe, Grandes-piles, Sainte-thècle, saint séverin | K42: Le-Fjord-du-Saguenay
A43: Simon | B43: Terres et bois | C43: 45658 | D43: 45836 | E43: Les Jardins-de-Napierville | G43: non | K43: Le Granit
A44: Simon | B44: Terres | C44: 45292 | D44: 45658 | E44: Les Jardins-de-Napierville | G44: oui | K44: Le Haut-Richelieu
A45: Eloi | B45: Terres et bois | C45: 45658 | D45: 45847 | E45: Bellechasse | G45: non | K45: Le Haut-Saint-François
A46: Simon | B46: Terres | C46: 45292 | D46: 45860 | F46: Jonquière | G46: oui | K46: Le Haut-Saint-Laurent
A47: Simon | B47: Terres et bois | C47: 45292 | D47: 45860 | F47: Chicoutimi | G47: non | K47: L'Érable
A48: Simon | B48: Terres et bois | C48: 44927 | D48: 45860 | F48: Saguenay | G48: non | K48: Le Rocher-Percé
A49: Simon | B49: Terres et bois | C49: 45292 | D49: 45860 | F49: La Baie | G49: non | K49: Les Appalaches
A50: Simon | B50: Terres | C50: 44562 | D50: 45292 | F50: Jonquière | G50: oui | K50: Les Basques
A51: Simon | B51: Terres | C51: 44562 | D51: 45292 | F51: Chicoutimi | G51: oui | K51: Les Collines-de-l'Outaouais
A52: Simon | B52: Terres | C52: 44562 | D52: 45292 | F52: La Baie | G52: oui | K52: Les Etchemins
A53: Eloi | B53: Terres et bois | C53: 45474 | D53: 45881 | E53: D'Autray | F53: Saint-cuthbert, saint geneviève, lanoraie | G53: non | K53: Les Jardins-de-Napierville
A54: Simon | B54: Bois | E54: Mékinac | K54: Les Laurentides
A55: Simon | B55: Bois | F55: La Tuque | K55: Les Maskoutains
A56: Simon | B56: Bois | C56: 44562 | D56: 45884 | E56: La Jacques-Cartier | H56: +100 ha | K56: Les Moulins
A57: Simon | B57: Bois | C57: 44562 | D57: 45884 | E57: La Côte-de-Beaupré | H57: +100 ha | K57: Les Pays-d'en-Haut
A58: Simon | B58: Bois | C58: 44562 | D58: 45884 | E58: Charlevoix | H58: +100 ha | K58: Lévis
A59: Simon | B59: Bois | C59: 44927 | D59: 45884 | E59: Charlevoix-Est | H59: +100 ha | K59: Les Sources
A60: Simon | B60: Bois | C60: 44927 | D60: 45884 | E60: Le Domaine-du-Roy | H60: +100 ha | K60: Le Val-Saint-François
A61: Simon | B61: Bois | C61: 44927 | D61: 45884 | E61: Lac-Saint-Jean-Est | H61: +100 ha | K61: L'Île-d'Orléans
A62: Simon | B62: Bois | C62: 44927 | D62: 45884 | E62: Le-Fjord-du-Saguenay | H62: +100 ha | K62: L'Islet
A63: Simon | B63: Bois | C63: 44927 | D63: 45884 | E63: Matawinie | H63: +100 ha | K63: Lotbinière
A64: Eloi | B64: Bois | C64: 44927 | D64: 45888 | E64: Vaudreuil-Soulanges | K64: Manicouagan
A65: Simon | B65: Terres et bois | C65: 43831 | D65: 45890 | F65: Boucherville | K65: Marguerite-D'Youville
A66: Simon | B66: Terres et bois | C66: 43831 | D66: 45890 | F66: Longueuil | K66: Maria-Chapdelaine
A67: Simon | B67: Terres et bois | C67: 43831 | D67: 45890 | F67: Brossard | K67: Maskinongé
A68: Simon | B68: Terres et bois | C68: 43831 | D68: 45890 | E68: La Vallée-du-Richelieu | K68: Matawinie
A69: Simon | B69: Terres et bois | C69: 43831 | D69: 45890 | F69: St-Amable | K69: Mékinac
A70: Simon | B70: Terres et bois | C70: 43831 | D70: 45890 | F70: Ste-Julie | K70: Memphrémagog
A71: Simon | B71: Terres | C71: 43831 | D71: 44197 | E71: Les Maskoutains | G71: oui | K71: Montcalm
A72: Simon | B72: Terres | C72: 44197 | D72: 45890 | E72: Rouville | G72: oui | K72: Montmagny
A73: Simon | B73: Terres | C73: 44197 | D73: 45890 | E73: Roussillon | G73: oui | K73: Nicolet-Yamaska
A74: Simon | B74: Terres | C74: 44562 | D74: 45979 | E74: Le Haut-Saint-François | G74: oui | K74: Papineau
A75: Simon | B75: Terres | C75: 45658 | D75: 45893 | E75: Coaticook | G75: oui | K75: Pierre-De Saurel
A76: Simon | B76: Terres | C76: 45658 | D76: 45893 | E76: Le Granit | G76: oui | K76: Pontiac
A77: Simon | B77: Terres | C77: 45658 | D77: 45893 | E77: Les Sources | G77: oui | K77: Portneuf
A78: Simon | B78: Terres | C78: 45658 | D78: 45979 | E78: Le Val-Saint-François | G78: oui | K78: Québec
A79: Simon | B79: Terres et bois | C79: 44562 | D79: 45893 | E79: Le Haut-Saint-François | K79: Rimouski-Neigette
A80: Eloi | B80: Terres et bois | C80: 45658 | D80: 45893 | E80: Le Haut-Saint-François | G80: FPE | K80: Rivière-du-Loup
A81: Eloi | B81: Terres et bois | C81: 45658 | D81: 45903 | E81: Beauce-Sartigan | K81: Robert-Cliche
A82: Eloi | B82: Terres et bois | C82: 45658 | D82: 45911 | E82: Montmagny | K82: Roussillon
A83: Simon | B83: Terres et bois | C83: 45631 | D83: 45914 | E83: La Mitis | G83: non | K83: Rouville
A84: Simon | B84: Bois | C84: 45292 | D84: 45631 | E84: La Mitis | K84: Témiscamingue
A85: Eloi | B85: Bois | C85: 44927 | D85: 45915 | E85: Montmagny | F85: Sainte-apolline-de-patton, Notre-dame-du-rosaire,cap-saint-ignace | K85: Témiscouata
A86: Eloi | B86: Bois | C86: 45627 | D86: 45923 | E86: L'Islet | K86: Thérèse-De Blainville
A87: Eloi | B87: Bois | C87: 45809 | D87: 45944 | E87: La Jacques-Cartier | G87: non | K87: Vaudreuil-Soulanges
A88: Eloi | B88: Terres | C88: 45292 | D88: 45946 | E88: La Jacques-Cartier | G88: oui | K88: Montmagny
A89: Simon | B89: Bois | C89: 44562 | D89: 45474 | F89: Lac-Des-Aigles
A90: Simon | B90: Bois | C90: 44562 | D90: 45474 | F90: Saint-Guy
A91: Simon | B91: Bois | C91: 44562 | D91: 45474 | F91: Biencourt
A92: Simon | B92: Bois | C92: 44562 | D92: 45474 | F92: Esprit-Saint
A93: Simon | C93: 44562 | D93: 45474 | E93: Rimouski-Neigette
A94: Simon | C94: 44562 | D94: 45474 | E94: Témiscouata
A95: Simon | C95: 44562 | D95: 45474 | E95: Les Basques
A96: Eloi | B96: Terres | C96: 44927 | D96: 45954 | E96: Le Haut-Richelieu | F96: Henryville Saint-blaise-sur-richelieu Saint-georges-de-clarenceville Saint-Alexandre Saint-Jean-sur-Richelieu
A97: Eloi | B97: Bois | C97: 44927 | D97: 45960 | E97: Portneuf | F97: Saint-Basile | J97: Bois- 10ha
A98: Simon | B98: Terres | C98: 45890 | D98: 45964 | E98: La Vallée-du-Richelieu | G98: oui
A99: Simon | B99: Terres | C99: 45890 | D99: 45964 | E99: Rouville | G99: oui
A100: Simon | B100: Bois | C100: 45292 | D100: 45965 | E100: Rouville
...
